{
"type": "FeatureCollection",
"name": "09BA001_PourPoint_PointExutoire",
"crs": { "type": "name", "properties": { "name": "urn:ogc:def:crs:OGC:1.3:CRS84" } },
"features": [
{ "type": "Feature", "properties": { "StationNum": "09BA001", "NameNom": "ROSS RIVER AT ROSS RIVER", "Status": "active", "Etat": "en service", "ProvTerr": "YT" }, "geometry": { "type": "Point", "coordinates": [ -132.408, 61.98816 ] } }
]
}
