{
"type": "FeatureCollection",
"name": "08NK022_dam_data",
"crs": { "type": "name", "properties": { "name": "urn:ogc:def:crs:EPSG::3005" } },
"features": [
{ "type": "Feature", "properties": { "Dam_ID": 2154, "Dam_Number": "D320116-00", "x": -114.7721187, "y": 49.9223065, "Source": "Water Rights Licences dataset: POD Number", "Date_Extracted": "2024-01-03T00:00:00", "Dam_Name": "WEST LINE CREEK DAM", "Points_Code": "PD23641", "Dam_Regulated_Code": "Non-Regulated - Including Minor Dam", "Dam_Operation_Code": "Active", "Function": "Main", "Actual_Storage": null, "Total_Licence_Storage": null, "Admin_Unit": "South Area - Kootenay", "Dam_Type": "Earthfill", "Dam_Height": 34.0, "Crest_Length": 0.0, "Crest_Elevation": 1530.0, "Centre_Position_UTM": 11.0, "Centre_Position_Easting": 659916.043, "Centre_Postion_Northing": 5532371.972, "Centre_Lat_Y": 49.9223065, "Centre_Long_X": -114.7721187, "Capable_to_withstand_MDE": null, "Low_Level_Outlet": null, "Spillway_Name": "Spillway 1", "Spillway_Type": "Concrete Overflow", "Design_Flood_Elevation": null, "Sill_Elevation": 0.0, "Capacity_at_DFE": 0.0, "Inflow_Design_Flood": null, "Owner_Name": "Elk Valley Coal Corportation (41924)", "Alternate_Contact_Name": null, "Compliance_with_Regulations": "Not Applicable", "DSO_Assigned": "ONeill, Kevin FLNR:EX", "Last_Audit_Date": null, "Years_Since_Last_Audit": null, "Audit_Status": null, "Audited_This_Year": null, "Regular_Site_Surveil_Confirm_Da": null, "Ann_Formal_Inspection_Confirm_D": null, "OMS_Version_Date": null, "OMS_Received_Date": null, "OMS_Accepted_Date": null, "DEP_Version_Date": null, "DEP_Received_Date": null, "DEP_Accepted_Date": null, "DSR_Version_Date": null, "DSR_Received_Date": null, "DSR_Accepted_Date": null, "Failure_Consequence": "Undetermined", "Risk_Level": null, "Failure_Probability_Rate": null, "Deficiency_Type": null, "Deficiency_Description": null, "Deficiency_Created_Date": null, "Deficiency_Resolved_Date": null, "Total_Key_Fields": 41, "Total_Filled": 18, "Total_Missing": 23.0, "Percent_Filled": 0.43902439 }, "geometry": { "type": "Point", "coordinates": [ 1802985.498500000685453, 608954.933299999684095 ] } }
]
}
