{
"type": "FeatureCollection",
"name": "05MH008_PourPoint_PointExutoire",
"crs": { "type": "name", "properties": { "name": "urn:ogc:def:crs:OGC:1.3:CRS84" } },
"features": [
{ "type": "Feature", "properties": { "StationNum": "05MH008", "NameNom": "CYPRESS RIVER NEAR BRUXELLES", "Status": "active", "Etat": "en service", "ProvTerr": "MB" }, "geometry": { "type": "Point", "coordinates": [ -98.90807, 49.44629 ] } }
]
}
