{
"type": "FeatureCollection",
"name": "08NG061_dam_data",
"crs": { "type": "name", "properties": { "name": "urn:ogc:def:crs:EPSG::3005" } },
"features": [
{ "type": "Feature", "properties": { "Dam_ID": 2167, "Dam_Number": "D310113-00", "x": -115.448658321, "y": 49.381099706599997, "Source": "E-Licensing: Derived Centre Point", "Date_Extracted": "2024-01-03T00:00:00", "Dam_Name": "CHIPKA CREEK DAM", "Points_Code": "PD23275", "Dam_Regulated_Code": "Regulated", "Dam_Operation_Code": "Active", "Function": "Main", "Actual_Storage": null, "Total_Licence_Storage": 61674.0, "Admin_Unit": "South Area - Kootenay", "Dam_Type": "Earthfill", "Dam_Height": 3.1, "Crest_Length": 38.1, "Crest_Elevation": 0.0, "Centre_Position_UTM": 11.0, "Centre_Position_Easting": 612598.731, "Centre_Postion_Northing": 5470979.441, "Centre_Lat_Y": 49.3810997, "Centre_Long_X": -115.4486583, "Capable_to_withstand_MDE": null, "Low_Level_Outlet": null, "Spillway_Name": "Spillway 1", "Spillway_Type": null, "Design_Flood_Elevation": null, "Sill_Elevation": 0.0, "Capacity_at_DFE": 0.0, "Inflow_Design_Flood": null, "Owner_Name": "David Karl Sandberg and Janet  Doris Sandberg (68532)", "Alternate_Contact_Name": "John E Takala and Jo Anne L Ponath (75669)", "Compliance_with_Regulations": "Unknown", "DSO_Assigned": "ONeill, Kevin FLNR:EX", "Last_Audit_Date": null, "Years_Since_Last_Audit": null, "Audit_Status": "Not Required", "Audited_This_Year": null, "Regular_Site_Surveil_Confirm_Da": null, "Ann_Formal_Inspection_Confirm_D": null, "OMS_Version_Date": null, "OMS_Received_Date": null, "OMS_Accepted_Date": null, "DEP_Version_Date": null, "DEP_Received_Date": null, "DEP_Accepted_Date": null, "DSR_Version_Date": null, "DSR_Received_Date": null, "DSR_Accepted_Date": null, "Failure_Consequence": "Low", "Risk_Level": "5 - Effectual", "Failure_Probability_Rate": "Small/Very Small", "Deficiency_Type": null, "Deficiency_Description": null, "Deficiency_Created_Date": null, "Deficiency_Resolved_Date": null, "Total_Key_Fields": 26, "Total_Filled": 19, "Total_Missing": 7.0, "Percent_Filled": 0.730769231 }, "geometry": { "type": "Point", "coordinates": [ 1763906.624399999156594, 542008.749299999326468 ] } }
]
}
