{
"type": "FeatureCollection",
"name": "06AF001_PourPoint_PointExutoire",
"crs": { "type": "name", "properties": { "name": "urn:ogc:def:crs:OGC:1.3:CRS84" } },
"features": [
{ "type": "Feature", "properties": { "StationNum": "06AF001", "NameNom": "COLD RIVER AT OUTLET OF COLD LAKE", "Status": "active", "Etat": "en service", "ProvTerr": "SK" }, "geometry": { "type": "Point", "coordinates": [ -109.8427, 54.56584 ] } }
]
}
