{
"type": "FeatureCollection",
"name": "02EC021_PourPoint_PointExutoire",
"crs": { "type": "name", "properties": { "name": "urn:ogc:def:crs:OGC:1.3:CRS84" } },
"features": [
{ "type": "Feature", "properties": { "StationNum": "02EC021", "NameNom": "UXBRIDGE BROOK NEAR UXBRIDGE", "Status": "active", "Etat": "en service", "ProvTerr": "ON" }, "geometry": { "type": "Point", "coordinates": [ -79.11282, 44.13799 ] } }
]
}
