{
"type": "FeatureCollection",
"name": "02GA005_PourPoint_PointExutoire",
"crs": { "type": "name", "properties": { "name": "urn:ogc:def:crs:OGC:1.3:CRS84" } },
"features": [
{ "type": "Feature", "properties": { "StationNum": "02GA005", "NameNom": "IRVINE RIVER NEAR SALEM", "Status": "active", "Etat": "en service", "ProvTerr": "ON" }, "geometry": { "type": "Point", "coordinates": [ -80.44538, 43.69359 ] } }
]
}
