{
"type": "FeatureCollection",
"name": "03NE012_PourPoint_PointExutoire",
"crs": { "type": "name", "properties": { "name": "urn:ogc:def:crs:OGC:1.3:CRS84" } },
"features": [
{ "type": "Feature", "properties": { "StationNum": "03NE012", "NameNom": "TRIBUTARY TO REID BROOK", "Status": "active", "Etat": "en service", "ProvTerr": "NL" }, "geometry": { "type": "Point", "coordinates": [ -62.09486, 56.30583 ] } }
]
}
