{
"type": "FeatureCollection",
"name": "08MH076_PourPoint_PointExutoire",
"crs": { "type": "name", "properties": { "name": "urn:ogc:def:crs:OGC:1.3:CRS84" } },
"features": [
{ "type": "Feature", "properties": { "StationNum": "08MH076", "NameNom": "KANAKA CREEK NEAR WEBSTER CORNERS", "Status": "active", "Etat": "en service", "ProvTerr": "BC" }, "geometry": { "type": "Point", "coordinates": [ -122.53639, 49.20664 ] } }
]
}
