{
"type": "FeatureCollection",
"name": "08KA013_Station",
"crs": { "type": "name", "properties": { "name": "urn:ogc:def:crs:OGC:1.3:CRS84" } },
"features": [
{ "type": "Feature", "properties": { "StationNum": "08KA013", "NameNom": "MORKILL RIVER BELOW HELLROARING CREEK", "Status": "active", "Etat": "en service", "ProvTerr": "BC", "HYDAT_ver": "2021-01" }, "geometry": { "type": "Point", "coordinates": [ -120.5914, 53.68167 ] } }
]
}
