{
"type": "FeatureCollection",
"name": "02HK017_Station",
"crs": { "type": "name", "properties": { "name": "urn:ogc:def:crs:OGC:1.3:CRS84" } },
"features": [
{ "type": "Feature", "properties": { "StationNum": "02HK017", "NameNom": "HOARDS CREEK NEAR WELLMAN", "Status": "active", "Etat": "en service", "ProvTerr": "ON", "HYDAT_ver": "2021-01" }, "geometry": { "type": "Point", "coordinates": [ -77.62841, 44.33176 ] } }
]
}
