{
"type": "FeatureCollection",
"name": "02FE017_Station",
"crs": { "type": "name", "properties": { "name": "urn:ogc:def:crs:OGC:1.3:CRS84" } },
"features": [
{ "type": "Feature", "properties": { "StationNum": "02FE017", "NameNom": "LAKELET CREEK NEAR GORRIE", "Status": "active", "Etat": "en service", "ProvTerr": "ON", "HYDAT_ver": "2021-01" }, "geometry": { "type": "Point", "coordinates": [ -81.06328, 43.89292 ] } }
]
}
