{
"type": "FeatureCollection",
"name": "08LF080_dam_data",
"crs": { "type": "name", "properties": { "name": "urn:ogc:def:crs:EPSG::3005" } },
"features": [
{ "type": "Feature", "properties": { "Dam_ID": 56, "Dam_Number": "D110252-00", "x": -121.6466916854, "y": 51.275065836000003, "Source": "E-Licensing: Derived Centre Point", "Date_Extracted": "2024-01-03T00:00:00", "Dam_Name": "BOOT MARSH DAM", "Points_Code": "PD45911", "Dam_Regulated_Code": "Regulated", "Dam_Operation_Code": "Active", "Function": "Main", "Actual_Storage": null, "Total_Licence_Storage": null, "Admin_Unit": "South Area - Thompson", "Dam_Type": "Earthfill", "Dam_Height": 3.4, "Crest_Length": 45.0, "Crest_Elevation": 1119.2, "Centre_Position_UTM": 10.0, "Centre_Position_Easting": 594396.622, "Centre_Postion_Northing": 5681283.772, "Centre_Lat_Y": 51.27506584, "Centre_Long_X": -121.6466917, "Capable_to_withstand_MDE": null, "Low_Level_Outlet": null, "Spillway_Name": "Spillway 1", "Spillway_Type": "Native Channel Overflow", "Design_Flood_Elevation": null, "Sill_Elevation": 1118.1, "Capacity_at_DFE": 0.0, "Inflow_Design_Flood": null, "Owner_Name": "Ducks Unlimited (Canada) (8359)", "Alternate_Contact_Name": "Katharine vanSpall", "Compliance_with_Regulations": "Yes", "DSO_Assigned": "Bennett, Darren J ENV:EX", "Last_Audit_Date": null, "Years_Since_Last_Audit": null, "Audit_Status": "Not Required", "Audited_This_Year": null, "Regular_Site_Surveil_Confirm_Da": "2023-09-19T00:00:00", "Ann_Formal_Inspection_Confirm_D": "2023-09-19T00:00:00", "OMS_Version_Date": null, "OMS_Received_Date": null, "OMS_Accepted_Date": null, "DEP_Version_Date": null, "DEP_Received_Date": null, "DEP_Accepted_Date": null, "DSR_Version_Date": null, "DSR_Received_Date": null, "DSR_Accepted_Date": null, "Failure_Consequence": "Low", "Risk_Level": "5 - Effectual", "Failure_Probability_Rate": "Small/Very Small", "Deficiency_Type": null, "Deficiency_Description": null, "Deficiency_Created_Date": null, "Deficiency_Resolved_Date": null, "Total_Key_Fields": 26, "Total_Filled": 19, "Total_Missing": 7.0, "Percent_Filled": 0.730769231 }, "geometry": { "type": "Point", "coordinates": [ 1303194.186799999326468, 705046.499600000679493 ] } }
]
}
