{
"type": "FeatureCollection",
"name": "04LM001_Station",
"crs": { "type": "name", "properties": { "name": "urn:ogc:def:crs:OGC:1.3:CRS84" } },
"features": [
{ "type": "Feature", "properties": { "StationNum": "04LM001", "NameNom": "MISSINAIBI RIVER BELOW WABOOSE RIVER", "Status": "active", "Etat": "en service", "ProvTerr": "ON", "HYDAT_ver": "2021-01" }, "geometry": { "type": "Point", "coordinates": [ -82.091, 50.58544 ] } }
]
}
