{
"type": "FeatureCollection",
"name": "01AF009_PourPoint_PointExutoire",
"crs": { "type": "name", "properties": { "name": "urn:ogc:def:crs:OGC:1.3:CRS84" } },
"features": [
{ "type": "Feature", "properties": { "StationNum": "01AF009", "NameNom": "IROQUOIS RIVER AT MOULIN MORNEAULT", "Status": "active", "Etat": "en service", "ProvTerr": "NB" }, "geometry": { "type": "Point", "coordinates": [ -68.35671, 47.45762 ] } }
]
}
