{
"type": "FeatureCollection",
"name": "08FF003_Station",
"crs": { "type": "name", "properties": { "name": "urn:ogc:def:crs:OGC:1.3:CRS84" } },
"features": [
{ "type": "Feature", "properties": { "StationNum": "08FF003", "NameNom": "LITTLE WEDEENE RIVER BELOW BOWBYES CREEK", "Status": "active", "Etat": "en service", "ProvTerr": "BC", "HYDAT_ver": "2021-01" }, "geometry": { "type": "Point", "coordinates": [ -128.69, 54.13639 ] } }
]
}
