{
"type": "FeatureCollection",
"name": "08KH031_Station",
"crs": { "type": "name", "properties": { "name": "urn:ogc:def:crs:OGC:1.3:CRS84" } },
"features": [
{ "type": "Feature", "properties": { "StationNum": "08KH031", "NameNom": "HORSEFLY RIVER ABOVE QUESNEL LAKE", "Status": "active", "Etat": "en service", "ProvTerr": "BC", "HYDAT_ver": "2021-01" }, "geometry": { "type": "Point", "coordinates": [ -121.4181, 52.44431 ] } }
]
}
