{
"type": "FeatureCollection",
"name": "08NG065_Station",
"crs": { "type": "name", "properties": { "name": "urn:ogc:def:crs:OGC:1.3:CRS84" } },
"features": [
{ "type": "Feature", "properties": { "StationNum": "08NG065", "NameNom": "KOOTENAY RIVER AT FORT STEELE", "Status": "active", "Etat": "en service", "ProvTerr": "BC", "HYDAT_ver": "2021-01" }, "geometry": { "type": "Point", "coordinates": [ -115.6353, 49.61203 ] } }
]
}
