{
"type": "FeatureCollection",
"name": "02FD003_Station",
"crs": { "type": "name", "properties": { "name": "urn:ogc:def:crs:OGC:1.3:CRS84" } },
"features": [
{ "type": "Feature", "properties": { "StationNum": "02FD003", "NameNom": "NORTH PENETANGORE RIVER AT KINCARDINE", "Status": "active", "Etat": "en service", "ProvTerr": "ON", "HYDAT_ver": "2021-01" }, "geometry": { "type": "Point", "coordinates": [ -81.63106, 44.17281 ] } }
]
}
