{
"type": "FeatureCollection",
"name": "02GG006_PourPoint_PointExutoire",
"crs": { "type": "name", "properties": { "name": "urn:ogc:def:crs:OGC:1.3:CRS84" } },
"features": [
{ "type": "Feature", "properties": { "StationNum": "02GG006", "NameNom": "BEAR CREEK NEAR PETROLIA", "Status": "active", "Etat": "en service", "ProvTerr": "ON" }, "geometry": { "type": "Point", "coordinates": [ -82.11895, 42.90576 ] } }
]
}
