{
"type": "FeatureCollection",
"name": "10AA005_PourPoint_PointExutoire",
"crs": { "type": "name", "properties": { "name": "urn:ogc:def:crs:OGC:1.3:CRS84" } },
"features": [
{ "type": "Feature", "properties": { "StationNum": "10AA005", "NameNom": "BIG CREEK AT KM 1084.8 ALASKA HIGHWAY", "Status": "active", "Etat": "en service", "ProvTerr": "YT" }, "geometry": { "type": "Point", "coordinates": [ -129.70421, 60.15816 ] } }
]
}
