{
"type": "FeatureCollection",
"name": "05CE018_Station",
"crs": { "type": "name", "properties": { "name": "urn:ogc:def:crs:OGC:1.3:CRS84" } },
"features": [
{ "type": "Feature", "properties": { "StationNum": "05CE018", "NameNom": "THREEHILLS CREEK BELOW RAY CREEK", "Status": "active", "Etat": "en service", "ProvTerr": "AB", "HYDAT_ver": "2021-01" }, "geometry": { "type": "Point", "coordinates": [ -113.5686, 51.99747 ] } }
]
}
