{
"type": "FeatureCollection",
"name": "07GE003_PourPoint_PointExutoire",
"crs": { "type": "name", "properties": { "name": "urn:ogc:def:crs:OGC:1.3:CRS84" } },
"features": [
{ "type": "Feature", "properties": { "StationNum": "07GE003", "NameNom": "GRANDE PRAIRIE CREEK NEAR SEXSMITH", "Status": "active", "Etat": "en service", "ProvTerr": "AB" }, "geometry": { "type": "Point", "coordinates": [ -118.91574, 55.3744 ] } }
]
}
