{
"type": "FeatureCollection",
"name": "05BG006_PourPoint_PointExutoire",
"crs": { "type": "name", "properties": { "name": "urn:ogc:def:crs:OGC:1.3:CRS84" } },
"features": [
{ "type": "Feature", "properties": { "StationNum": "05BG006", "NameNom": "WAIPAROUS CREEK NEAR THE MOUTH", "Status": "active", "Etat": "en service", "ProvTerr": "AB" }, "geometry": { "type": "Point", "coordinates": [ -114.83834, 51.28302 ] } }
]
}
