{
"type": "FeatureCollection",
"name": "05BL027_PourPoint_PointExutoire",
"crs": { "type": "name", "properties": { "name": "urn:ogc:def:crs:OGC:1.3:CRS84" } },
"features": [
{ "type": "Feature", "properties": { "StationNum": "05BL027", "NameNom": "TRAP CREEK NEAR LONGVIEW", "Status": "active", "Etat": "en service", "ProvTerr": "AB" }, "geometry": { "type": "Point", "coordinates": [ -114.42585, 50.47724 ] } }
]
}
