{
"type": "FeatureCollection",
"name": "06FD002_PourPoint_PointExutoire",
"crs": { "type": "name", "properties": { "name": "urn:ogc:def:crs:OGC:1.3:CRS84" } },
"features": [
{ "type": "Feature", "properties": { "StationNum": "06FD002", "NameNom": "DEER RIVER NORTH OF BELCHER", "Status": "active", "Etat": "en service", "ProvTerr": "MB" }, "geometry": { "type": "Point", "coordinates": [ -94.19742, 58.01345 ] } }
]
}
