{
"type": "FeatureCollection",
"name": "02YL005_Station",
"crs": { "type": "name", "properties": { "name": "urn:ogc:def:crs:OGC:1.3:CRS84" } },
"features": [
{ "type": "Feature", "properties": { "StationNum": "02YL005", "NameNom": "RATTLER BROOK NEAR MCIVERS", "Status": "active", "Etat": "en service", "ProvTerr": "NL", "HYDAT_ver": "2021-01" }, "geometry": { "type": "Point", "coordinates": [ -58.10519, 49.05831 ] } }
]
}
