{
"type": "FeatureCollection",
"name": "01BS001_PourPoint_PointExutoire",
"crs": { "type": "name", "properties": { "name": "urn:ogc:def:crs:OGC:1.3:CRS84" } },
"features": [
{ "type": "Feature", "properties": { "StationNum": "01BS001", "NameNom": "COAL BRANCH RIVER AT BEERSVILLE", "Status": "active", "Etat": "en service", "ProvTerr": "NB" }, "geometry": { "type": "Point", "coordinates": [ -65.06444, 46.44387 ] } }
]
}
