{
"type": "FeatureCollection",
"name": "05QE008_Station",
"crs": { "type": "name", "properties": { "name": "urn:ogc:def:crs:OGC:1.3:CRS84" } },
"features": [
{ "type": "Feature", "properties": { "StationNum": "05QE008", "NameNom": "CEDAR RIVER BELOW WABASKANG LAKE", "Status": "active", "Etat": "en service", "ProvTerr": "ON", "HYDAT_ver": "2021-01" }, "geometry": { "type": "Point", "coordinates": [ -93.25858, 50.50756 ] } }
]
}
