{
"type": "FeatureCollection",
"name": "02ZJ003_PourPoint_PointExutoire",
"crs": { "type": "name", "properties": { "name": "urn:ogc:def:crs:OGC:1.3:CRS84" } },
"features": [
{ "type": "Feature", "properties": { "StationNum": "02ZJ003", "NameNom": "SHOAL HARBOUR RIVER NEAR CLARENVILLE", "Status": "active", "Etat": "en service", "ProvTerr": "NL" }, "geometry": { "type": "Point", "coordinates": [ -54.04936, 48.22034 ] } }
]
}
