{
"type": "FeatureCollection",
"name": "05LC004_Station",
"crs": { "type": "name", "properties": { "name": "urn:ogc:def:crs:OGC:1.3:CRS84" } },
"features": [
{ "type": "Feature", "properties": { "StationNum": "05LC004", "NameNom": "RED DEER RIVER NEAR THE MOUTH", "Status": "active", "Etat": "en service", "ProvTerr": "MB", "HYDAT_ver": "2021-01" }, "geometry": { "type": "Point", "coordinates": [ -101.0494, 52.87628 ] } }
]
}
