{
"type": "FeatureCollection",
"name": "08AB001_PourPoint_PointExutoire",
"crs": { "type": "name", "properties": { "name": "urn:ogc:def:crs:OGC:1.3:CRS84" } },
"features": [
{ "type": "Feature", "properties": { "StationNum": "08AB001", "NameNom": "ALSEK RIVER ABOVE BATES RIVER", "Status": "active", "Etat": "en service", "ProvTerr": "YT" }, "geometry": { "type": "Point", "coordinates": [ -137.97601, 60.11807 ] } }
]
}
