{
"type": "FeatureCollection",
"name": "10EB001_PourPoint_PointExutoire",
"crs": { "type": "name", "properties": { "name": "urn:ogc:def:crs:OGC:1.3:CRS84" } },
"features": [
{ "type": "Feature", "properties": { "StationNum": "10EB001", "NameNom": "SOUTH NAHANNI RIVER ABOVE VIRGINIA FALLS", "Status": "active", "Etat": "en service", "ProvTerr": "NT" }, "geometry": { "type": "Point", "coordinates": [ -125.79932, 61.63593 ] } }
]
}
