{
"type": "FeatureCollection",
"name": "11AC025_PourPoint_PointExutoire",
"crs": { "type": "name", "properties": { "name": "urn:ogc:def:crs:OGC:1.3:CRS84" } },
"features": [
{ "type": "Feature", "properties": { "StationNum": "11AC025", "NameNom": "DENNIEL CREEK NEAR VAL MARIE", "Status": "active", "Etat": "en service", "ProvTerr": "SK" }, "geometry": { "type": "Point", "coordinates": [ -107.70352, 49.30693 ] } }
]
}
