{
"type": "FeatureCollection",
"name": "08HB037_dam_data",
"crs": { "type": "name", "properties": { "name": "urn:ogc:def:crs:EPSG::3005" } },
"features": [
{ "type": "Feature", "properties": { "Dam_ID": 2246, "Dam_Number": "D720143-00", "x": -124.7374172169, "y": 49.487785122200002, "Source": "E-Licensing: Derived Centre Point", "Date_Extracted": "2024-01-03T00:00:00", "Dam_Name": "LACON LAKE DAM", "Points_Code": "PD31335", "Dam_Regulated_Code": "Regulated", "Dam_Operation_Code": "Active", "Function": "Conversion", "Actual_Storage": null, "Total_Licence_Storage": 22202.64, "Admin_Unit": "Coast - West Coast", "Dam_Type": "Earthfill", "Dam_Height": 3.0, "Crest_Length": 40.0, "Crest_Elevation": 0.0, "Centre_Position_UTM": 10.0, "Centre_Position_Easting": 374169.5, "Centre_Postion_Northing": 5483133.5, "Centre_Lat_Y": 49.48778512, "Centre_Long_X": -124.7374172, "Capable_to_withstand_MDE": null, "Low_Level_Outlet": null, "Spillway_Name": "Spillway 1", "Spillway_Type": "Culvert", "Design_Flood_Elevation": null, "Sill_Elevation": 0.0, "Capacity_at_DFE": 0.0, "Inflow_Design_Flood": null, "Owner_Name": "James A Noakes and Cathy N Noakes (76991)", "Alternate_Contact_Name": null, "Compliance_with_Regulations": "Yes", "DSO_Assigned": "Johnson, David A FLNR:EX", "Last_Audit_Date": "2008-10-23T00:00:00", "Years_Since_Last_Audit": 15.2, "Audit_Status": "Not Required", "Audited_This_Year": "No", "Regular_Site_Surveil_Confirm_Da": null, "Ann_Formal_Inspection_Confirm_D": null, "OMS_Version_Date": null, "OMS_Received_Date": null, "OMS_Accepted_Date": null, "DEP_Version_Date": null, "DEP_Received_Date": null, "DEP_Accepted_Date": null, "DSR_Version_Date": null, "DSR_Received_Date": null, "DSR_Accepted_Date": null, "Failure_Consequence": "Low", "Risk_Level": "5 - Effectual", "Failure_Probability_Rate": "Small/Very Small", "Deficiency_Type": null, "Deficiency_Description": null, "Deficiency_Created_Date": null, "Deficiency_Resolved_Date": null, "Total_Key_Fields": 26, "Total_Filled": 21, "Total_Missing": 5.0, "Percent_Filled": 0.807692308 }, "geometry": { "type": "Point", "coordinates": [ 1091532.736300000920892, 497647.2807 ] } }
]
}
