{
"type": "FeatureCollection",
"name": "02LB020_Station",
"crs": { "type": "name", "properties": { "name": "urn:ogc:def:crs:OGC:1.3:CRS84" } },
"features": [
{ "type": "Feature", "properties": { "StationNum": "02LB020", "NameNom": "SOUTH CASTOR RIVER AT KENMORE", "Status": "active", "Etat": "en service", "ProvTerr": "ON", "HYDAT_ver": "2021-01" }, "geometry": { "type": "Point", "coordinates": [ -75.41272, 45.22833 ] } }
]
}
