{
"type": "FeatureCollection",
"name": "02YE001_PourPoint_PointExutoire",
"crs": { "type": "name", "properties": { "name": "urn:ogc:def:crs:OGC:1.3:CRS84" } },
"features": [
{ "type": "Feature", "properties": { "StationNum": "02YE001", "NameNom": "GREAVETT BROOK ABOVE PORTLAND CREEK POND", "Status": "active", "Etat": "en service", "ProvTerr": "NL" }, "geometry": { "type": "Point", "coordinates": [ -57.57747, 50.16211 ] } }
]
}
