{
"type": "FeatureCollection",
"name": "08NN023_PourPoint_PointExutoire",
"crs": { "type": "name", "properties": { "name": "urn:ogc:def:crs:OGC:1.3:CRS84" } },
"features": [
{ "type": "Feature", "properties": { "StationNum": "08NN023", "NameNom": "BURRELL CREEK ABOVE GLOUCESTER CREEK", "Status": "active", "Etat": "en service", "ProvTerr": "BC" }, "geometry": { "type": "Point", "coordinates": [ -118.31206, 49.5888 ] } }
]
}
