{
"type": "FeatureCollection",
"name": "05QA004_PourPoint_PointExutoire",
"crs": { "type": "name", "properties": { "name": "urn:ogc:def:crs:OGC:1.3:CRS84" } },
"features": [
{ "type": "Feature", "properties": { "StationNum": "05QA004", "NameNom": "STURGEON RIVER AT MCDOUGALL MILLS", "Status": "active", "Etat": "en service", "ProvTerr": "ON" }, "geometry": { "type": "Point", "coordinates": [ -91.54132, 50.16791 ] } }
]
}
