{
"type": "FeatureCollection",
"name": "07FD009_PourPoint_PointExutoire",
"crs": { "type": "name", "properties": { "name": "urn:ogc:def:crs:OGC:1.3:CRS84" } },
"features": [
{ "type": "Feature", "properties": { "StationNum": "07FD009", "NameNom": "CLEAR RIVER NEAR BEAR CANYON", "Status": "active", "Etat": "en service", "ProvTerr": "AB" }, "geometry": { "type": "Point", "coordinates": [ -119.68103, 56.30775 ] } }
]
}
