{
"type": "FeatureCollection",
"name": "05DA007_PourPoint_PointExutoire",
"crs": { "type": "name", "properties": { "name": "urn:ogc:def:crs:OGC:1.3:CRS84" } },
"features": [
{ "type": "Feature", "properties": { "StationNum": "05DA007", "NameNom": "MISTAYA RIVER NEAR SASKATCHEWAN CROSSING", "Status": "active", "Etat": "en service", "ProvTerr": "AB" }, "geometry": { "type": "Point", "coordinates": [ -116.68985, 51.88386 ] } }
]
}
