{
"type": "FeatureCollection",
"name": "05DA007_Station",
"crs": { "type": "name", "properties": { "name": "urn:ogc:def:crs:OGC:1.3:CRS84" } },
"features": [
{ "type": "Feature", "properties": { "StationNum": "05DA007", "NameNom": "MISTAYA RIVER NEAR SASKATCHEWAN CROSSING", "Status": "active", "Etat": "en service", "ProvTerr": "AB", "HYDAT_ver": "2021-01" }, "geometry": { "type": "Point", "coordinates": [ -116.6892, 51.88427 ] } }
]
}
