{
"type": "FeatureCollection",
"name": "07EE009_PourPoint_PointExutoire",
"crs": { "type": "name", "properties": { "name": "urn:ogc:def:crs:OGC:1.3:CRS84" } },
"features": [
{ "type": "Feature", "properties": { "StationNum": "07EE009", "NameNom": "CHUCHINKA CREEK NEAR THE MOUTH", "Status": "active", "Etat": "en service", "ProvTerr": "BC" }, "geometry": { "type": "Point", "coordinates": [ -122.61275, 54.52971 ] } }
]
}
