{
"type": "FeatureCollection",
"name": "02FB014_Station",
"crs": { "type": "name", "properties": { "name": "urn:ogc:def:crs:OGC:1.3:CRS84" } },
"features": [
{ "type": "Feature", "properties": { "StationNum": "02FB014", "NameNom": "BIGHEAD RIVER NEAR STRATHAVON", "Status": "active", "Etat": "en service", "ProvTerr": "ON", "HYDAT_ver": "2021-01" }, "geometry": { "type": "Point", "coordinates": [ -80.77653, 44.47178 ] } }
]
}
