{
"type": "FeatureCollection",
"name": "05LG004_Station",
"crs": { "type": "name", "properties": { "name": "urn:ogc:def:crs:OGC:1.3:CRS84" } },
"features": [
{ "type": "Feature", "properties": { "StationNum": "05LG004", "NameNom": "NORTH DUCK RIVER AT COWAN", "Status": "active", "Etat": "en service", "ProvTerr": "MB", "HYDAT_ver": "2021-01" }, "geometry": { "type": "Point", "coordinates": [ -100.65, 52.03133 ] } }
]
}
