{
"type": "FeatureCollection",
"name": "08LF095_dam_data",
"crs": { "type": "name", "properties": { "name": "urn:ogc:def:crs:EPSG::3005" } },
"features": [
{ "type": "Feature", "properties": { "Dam_ID": 44, "Dam_Number": "D110222-00", "x": -120.6212545994, "y": 51.421754662600001, "Source": "E-Licensing: Derived Centre Point", "Date_Extracted": "2024-01-03T00:00:00", "Dam_Name": "MCDONALD CREEK DAM", "Points_Code": "PD37964", "Dam_Regulated_Code": "Regulated", "Dam_Operation_Code": "Active", "Function": "Main", "Actual_Storage": null, "Total_Licence_Storage": null, "Admin_Unit": "South Area - Thompson", "Dam_Type": "Earthfill", "Dam_Height": 0.0, "Crest_Length": 0.0, "Crest_Elevation": 0.0, "Centre_Position_UTM": 10.0, "Centre_Position_Easting": 665387.293, "Centre_Postion_Northing": 5699411.908, "Centre_Lat_Y": 51.42175466, "Centre_Long_X": -120.6212546, "Capable_to_withstand_MDE": null, "Low_Level_Outlet": null, "Spillway_Name": "Spillway 1", "Spillway_Type": null, "Design_Flood_Elevation": null, "Sill_Elevation": 0.0, "Capacity_at_DFE": 0.0, "Inflow_Design_Flood": null, "Owner_Name": "Ducks Unlimited (Canada) (8359)", "Alternate_Contact_Name": "Katharine vanSpall", "Compliance_with_Regulations": "No", "DSO_Assigned": "Bennett, Darren J ENV:EX", "Last_Audit_Date": null, "Years_Since_Last_Audit": null, "Audit_Status": "No Data", "Audited_This_Year": "No Data", "Regular_Site_Surveil_Confirm_Da": null, "Ann_Formal_Inspection_Confirm_D": null, "OMS_Version_Date": null, "OMS_Received_Date": null, "OMS_Accepted_Date": null, "DEP_Version_Date": null, "DEP_Received_Date": null, "DEP_Accepted_Date": null, "DSR_Version_Date": null, "DSR_Received_Date": null, "DSR_Accepted_Date": null, "Failure_Consequence": "Significant", "Risk_Level": "4 - No Concerns", "Failure_Probability_Rate": "Small", "Deficiency_Type": null, "Deficiency_Description": null, "Deficiency_Created_Date": null, "Deficiency_Resolved_Date": null, "Total_Key_Fields": 35, "Total_Filled": 19, "Total_Missing": 16.0, "Percent_Filled": 0.542857143 }, "geometry": { "type": "Point", "coordinates": [ 1373247.811699999496341, 726249.843100000172853 ] } },
{ "type": "Feature", "properties": { "Dam_ID": 42, "Dam_Number": "D110220-00", "x": -120.6325573697, "y": 51.419316159799997, "Source": "E-Licensing: Derived Centre Point", "Date_Extracted": "2024-01-03T00:00:00", "Dam_Name": "MONTANA CREEK DAM", "Points_Code": "PD37965", "Dam_Regulated_Code": "Regulated", "Dam_Operation_Code": "Active", "Function": "Main", "Actual_Storage": null, "Total_Licence_Storage": null, "Admin_Unit": "South Area - Thompson", "Dam_Type": "Earthfill", "Dam_Height": 0.0, "Crest_Length": 0.0, "Crest_Elevation": 0.0, "Centre_Position_UTM": 10.0, "Centre_Position_Easting": 664610.307, "Centre_Postion_Northing": 5699115.312, "Centre_Lat_Y": 51.41931616, "Centre_Long_X": -120.6325574, "Capable_to_withstand_MDE": null, "Low_Level_Outlet": null, "Spillway_Name": "Spillway 1", "Spillway_Type": null, "Design_Flood_Elevation": null, "Sill_Elevation": 0.0, "Capacity_at_DFE": 0.0, "Inflow_Design_Flood": null, "Owner_Name": "Ducks Unlimited (Canada) (8359)", "Alternate_Contact_Name": "Katharine vanSpall", "Compliance_with_Regulations": "Unknown", "DSO_Assigned": "Bennett, Darren J ENV:EX", "Last_Audit_Date": null, "Years_Since_Last_Audit": null, "Audit_Status": "Not Required", "Audited_This_Year": null, "Regular_Site_Surveil_Confirm_Da": null, "Ann_Formal_Inspection_Confirm_D": null, "OMS_Version_Date": null, "OMS_Received_Date": null, "OMS_Accepted_Date": null, "DEP_Version_Date": null, "DEP_Received_Date": null, "DEP_Accepted_Date": null, "DSR_Version_Date": null, "DSR_Received_Date": null, "DSR_Accepted_Date": null, "Failure_Consequence": "Low", "Risk_Level": "5 - Effectual", "Failure_Probability_Rate": "Small/Very Small", "Deficiency_Type": null, "Deficiency_Description": null, "Deficiency_Created_Date": null, "Deficiency_Resolved_Date": null, "Total_Key_Fields": 26, "Total_Filled": 18, "Total_Missing": 8.0, "Percent_Filled": 0.692307692 }, "geometry": { "type": "Point", "coordinates": [ 1372485.56220000050962, 725919.405600000172853 ] } }
]
}
