{
"type": "FeatureCollection",
"name": "02HB022_Station",
"crs": { "type": "name", "properties": { "name": "urn:ogc:def:crs:OGC:1.3:CRS84" } },
"features": [
{ "type": "Feature", "properties": { "StationNum": "02HB022", "NameNom": "BRONTE CREEK AT CARLISLE", "Status": "active", "Etat": "en service", "ProvTerr": "ON", "HYDAT_ver": "2021-01" }, "geometry": { "type": "Point", "coordinates": [ -79.98811, 43.38886 ] } }
]
}
