{
"type": "FeatureCollection",
"name": "02ZL005_PourPoint_PointExutoire",
"crs": { "type": "name", "properties": { "name": "urn:ogc:def:crs:OGC:1.3:CRS84" } },
"features": [
{ "type": "Feature", "properties": { "StationNum": "02ZL005", "NameNom": "BIG BROOK AT LEAD COVE", "Status": "active", "Etat": "en service", "ProvTerr": "NL" }, "geometry": { "type": "Point", "coordinates": [ -53.08233, 48.04285 ] } }
]
}
