{
"type": "FeatureCollection",
"name": "08NA001_dam_data",
"crs": { "type": "name", "properties": { "name": "urn:ogc:def:crs:EPSG::3005" } },
"features": [
{ "type": "Feature", "properties": { "Dam_ID": 3263, "Dam_Number": "D330002-00", "x": -116.4525962556, "y": 50.883612417800002, "Source": "E-Licensing: West Abut Only Coordinate", "Date_Extracted": "2024-01-03T00:00:00", "Dam_Name": "Bugaboo Diversion Dam", "Points_Code": "PD24224", "Dam_Regulated_Code": "Non-Regulated - Including Minor Dam", "Dam_Operation_Code": "Active", "Function": "Main", "Actual_Storage": null, "Total_Licence_Storage": 58297.96524, "Admin_Unit": "Dam Safety Section", "Dam_Type": "Earthfill", "Dam_Height": 4.7, "Crest_Length": null, "Crest_Elevation": 1003.2, "Centre_Position_UTM": 11.0, "Centre_Position_Easting": 538507.0, "Centre_Postion_Northing": 5637025.0, "Centre_Lat_Y": 50.88361242, "Centre_Long_X": -116.4525963, "Capable_to_withstand_MDE": null, "Low_Level_Outlet": null, "Spillway_Name": null, "Spillway_Type": null, "Design_Flood_Elevation": null, "Sill_Elevation": null, "Capacity_at_DFE": null, "Inflow_Design_Flood": null, "Owner_Name": "BC Hydro & Power Authority (64404)", "Alternate_Contact_Name": "Peter Gaffran (80114)", "Compliance_with_Regulations": "Yes", "DSO_Assigned": "Noseworthy, Mike ENV:EX", "Last_Audit_Date": null, "Years_Since_Last_Audit": null, "Audit_Status": null, "Audited_This_Year": null, "Regular_Site_Surveil_Confirm_Da": null, "Ann_Formal_Inspection_Confirm_D": "2021-01-08T00:00:00", "OMS_Version_Date": null, "OMS_Received_Date": null, "OMS_Accepted_Date": null, "DEP_Version_Date": null, "DEP_Received_Date": null, "DEP_Accepted_Date": null, "DSR_Version_Date": null, "DSR_Received_Date": null, "DSR_Accepted_Date": null, "Failure_Consequence": null, "Risk_Level": "6 - None", "Failure_Probability_Rate": null, "Deficiency_Type": null, "Deficiency_Description": null, "Deficiency_Created_Date": null, "Deficiency_Resolved_Date": null, "Total_Key_Fields": 41, "Total_Filled": 17, "Total_Missing": 24.0, "Percent_Filled": 0.414634146 }, "geometry": { "type": "Point", "coordinates": [ 1669212.73200000077486, 697318.392599999904633 ] } }
]
}
