{
"type": "FeatureCollection",
"name": "02ZE004_PourPoint_PointExutoire",
"crs": { "type": "name", "properties": { "name": "urn:ogc:def:crs:OGC:1.3:CRS84" } },
"features": [
{ "type": "Feature", "properties": { "StationNum": "02ZE004", "NameNom": "CONNE RIVER AT OUTLET OF CONNE RIVER POND", "Status": "active", "Etat": "en service", "ProvTerr": "NL" }, "geometry": { "type": "Point", "coordinates": [ -55.48245, 48.16854 ] } }
]
}
