{
"type": "FeatureCollection",
"name": "02ZD002_Station",
"crs": { "type": "name", "properties": { "name": "urn:ogc:def:crs:OGC:1.3:CRS84" } },
"features": [
{ "type": "Feature", "properties": { "StationNum": "02ZD002", "NameNom": "GREY RIVER NEAR GREY RIVER", "Status": "active", "Etat": "en service", "ProvTerr": "NL", "HYDAT_ver": "2021-01" }, "geometry": { "type": "Point", "coordinates": [ -56.934, 47.74331 ] } }
]
}
