{
"type": "FeatureCollection",
"name": "02AB017_Station",
"crs": { "type": "name", "properties": { "name": "urn:ogc:def:crs:OGC:1.3:CRS84" } },
"features": [
{ "type": "Feature", "properties": { "StationNum": "02AB017", "NameNom": "WHITEFISH RIVER AT NOLALU", "Status": "active", "Etat": "en service", "ProvTerr": "ON", "HYDAT_ver": "2021-01" }, "geometry": { "type": "Point", "coordinates": [ -89.80986, 48.29211 ] } }
]
}
