{
"type": "FeatureCollection",
"name": "05RE001_Station",
"crs": { "type": "name", "properties": { "name": "urn:ogc:def:crs:OGC:1.3:CRS84" } },
"features": [
{ "type": "Feature", "properties": { "StationNum": "05RE001", "NameNom": "POPLAR RIVER AT OUTLET OF WEAVER LAKE", "Status": "discontinued", "Etat": "fermée", "ProvTerr": "MB", "HYDAT_ver": "2021-01" }, "geometry": { "type": "Point", "coordinates": [ -96.75278, 52.77778 ] } }
]
}
