{
"type": "FeatureCollection",
"name": "08OA002_Station",
"crs": { "type": "name", "properties": { "name": "urn:ogc:def:crs:OGC:1.3:CRS84" } },
"features": [
{ "type": "Feature", "properties": { "StationNum": "08OA002", "NameNom": "YAKOUN RIVER NEAR PORT CLEMENTS", "Status": "active", "Etat": "en service", "ProvTerr": "BC", "HYDAT_ver": "2021-01" }, "geometry": { "type": "Point", "coordinates": [ -132.2097, 53.61389 ] } }
]
}
