{
"type": "FeatureCollection",
"name": "05LE006_Station",
"crs": { "type": "name", "properties": { "name": "urn:ogc:def:crs:OGC:1.3:CRS84" } },
"features": [
{ "type": "Feature", "properties": { "StationNum": "05LE006", "NameNom": "SWAN RIVER NEAR MINITONAS", "Status": "active", "Etat": "en service", "ProvTerr": "MB", "HYDAT_ver": "2021-01" }, "geometry": { "type": "Point", "coordinates": [ -101.0608, 52.196 ] } }
]
}
