{
"type": "FeatureCollection",
"name": "02MB010_Station",
"crs": { "type": "name", "properties": { "name": "urn:ogc:def:crs:OGC:1.3:CRS84" } },
"features": [
{ "type": "Feature", "properties": { "StationNum": "02MB010", "NameNom": "BUELLS CREEK AT BROCKVILLE", "Status": "active", "Etat": "en service", "ProvTerr": "ON", "HYDAT_ver": "2021-01" }, "geometry": { "type": "Point", "coordinates": [ -75.69178, 44.58569 ] } }
]
}
