{
"type": "FeatureCollection",
"name": "07HA005_PourPoint_PointExutoire",
"crs": { "type": "name", "properties": { "name": "urn:ogc:def:crs:OGC:1.3:CRS84" } },
"features": [
{ "type": "Feature", "properties": { "StationNum": "07HA005", "NameNom": "WHITEMUD RIVER NEAR DIXONVILLE", "Status": "active", "Etat": "en service", "ProvTerr": "AB" }, "geometry": { "type": "Point", "coordinates": [ -117.66091, 56.51101 ] } }
]
}
