{
"type": "FeatureCollection",
"name": "02ZG004_PourPoint_PointExutoire",
"crs": { "type": "name", "properties": { "name": "urn:ogc:def:crs:OGC:1.3:CRS84" } },
"features": [
{ "type": "Feature", "properties": { "StationNum": "02ZG004", "NameNom": "RATTLE BROOK NEAR BOAT HARBOUR", "Status": "active", "Etat": "en service", "ProvTerr": "NL" }, "geometry": { "type": "Point", "coordinates": [ -54.8524, 47.44759 ] } }
]
}
