{
"type": "FeatureCollection",
"name": "09AA006_Station",
"crs": { "type": "name", "properties": { "name": "urn:ogc:def:crs:OGC:1.3:CRS84" } },
"features": [
{ "type": "Feature", "properties": { "StationNum": "09AA006", "NameNom": "ATLIN RIVER NEAR ATLIN", "Status": "active", "Etat": "en service", "ProvTerr": "BC", "HYDAT_ver": "2021-01" }, "geometry": { "type": "Point", "coordinates": [ -133.8144, 59.59536 ] } }
]
}
