{
"type": "FeatureCollection",
"name": "02HM004_Station",
"crs": { "type": "name", "properties": { "name": "urn:ogc:def:crs:OGC:1.3:CRS84" } },
"features": [
{ "type": "Feature", "properties": { "StationNum": "02HM004", "NameNom": "WILTON CREEK NEAR NAPANEE", "Status": "active", "Etat": "en service", "ProvTerr": "ON", "HYDAT_ver": "2021-01" }, "geometry": { "type": "Point", "coordinates": [ -76.84922, 44.23943 ] } }
]
}
