{
"type": "FeatureCollection",
"name": "10FB005_Station",
"crs": { "type": "name", "properties": { "name": "urn:ogc:def:crs:OGC:1.3:CRS84" } },
"features": [
{ "type": "Feature", "properties": { "StationNum": "10FB005", "NameNom": "JEAN-MARIE RIVER AT HIGHWAY NO. 1", "Status": "active", "Etat": "en service", "ProvTerr": "NT", "HYDAT_ver": "2021-01" }, "geometry": { "type": "Point", "coordinates": [ -121.2382, 61.44553 ] } }
]
}
