{
"type": "FeatureCollection",
"name": "02GD019_Station",
"crs": { "type": "name", "properties": { "name": "urn:ogc:def:crs:OGC:1.3:CRS84" } },
"features": [
{ "type": "Feature", "properties": { "StationNum": "02GD019", "NameNom": "TROUT CREEK NEAR FAIRVIEW", "Status": "active", "Etat": "en service", "ProvTerr": "ON", "HYDAT_ver": "2021-01" }, "geometry": { "type": "Point", "coordinates": [ -80.97303, 43.29558 ] } }
]
}
