{
"type": "FeatureCollection",
"name": "08HA003_dam_data",
"crs": { "type": "name", "properties": { "name": "urn:ogc:def:crs:EPSG::3005" } },
"features": [
{ "type": "Feature", "properties": { "Dam_ID": 3289, "Dam_Number": "D730217-00", "x": -123.77270912100001, "y": 48.6261172918, "Source": "E-Licensing: Derived Centre Point", "Date_Extracted": "2024-01-03T00:00:00", "Dam_Name": "Grant Lake Dam", "Points_Code": "PD186008", "Dam_Regulated_Code": "Regulated", "Dam_Operation_Code": "Active", "Function": "Main", "Actual_Storage": null, "Total_Licence_Storage": 311000.0, "Admin_Unit": "Coast - West Coast", "Dam_Type": "Concrete–gravity", "Dam_Height": 1.0, "Crest_Length": 8.0, "Crest_Elevation": null, "Centre_Position_UTM": 10.0, "Centre_Position_Easting": 443060.5, "Centre_Postion_Northing": 5386182.5, "Centre_Lat_Y": 48.62611729, "Centre_Long_X": -123.7727091, "Capable_to_withstand_MDE": null, "Low_Level_Outlet": null, "Spillway_Name": null, "Spillway_Type": null, "Design_Flood_Elevation": null, "Sill_Elevation": null, "Capacity_at_DFE": null, "Inflow_Design_Flood": null, "Owner_Name": "Athena von Alberich (165097), Fran von Alberich, Lawrence von Alberich (165095), Lyle E Holroyd (72738)", "Alternate_Contact_Name": "Heinrich Spilker", "Compliance_with_Regulations": "No", "DSO_Assigned": "Johnson, David A FLNR:EX", "Last_Audit_Date": "2013-03-11T00:00:00", "Years_Since_Last_Audit": 10.8, "Audit_Status": "Backlog", "Audited_This_Year": "No", "Regular_Site_Surveil_Confirm_Da": "2021-08-25T00:00:00", "Ann_Formal_Inspection_Confirm_D": "2021-09-23T00:00:00", "OMS_Version_Date": null, "OMS_Received_Date": null, "OMS_Accepted_Date": null, "DEP_Version_Date": null, "DEP_Received_Date": null, "DEP_Accepted_Date": null, "DSR_Version_Date": null, "DSR_Received_Date": null, "DSR_Accepted_Date": null, "Failure_Consequence": "Significant", "Risk_Level": "4 - No Concerns", "Failure_Probability_Rate": "Small", "Deficiency_Type": null, "Deficiency_Description": null, "Deficiency_Created_Date": null, "Deficiency_Resolved_Date": null, "Total_Key_Fields": 35, "Total_Filled": 21, "Total_Missing": 14.0, "Percent_Filled": 0.6 }, "geometry": { "type": "Point", "coordinates": [ 1164463.3498, 403707.726099999621511 ] } }
]
}
