{
"type": "FeatureCollection",
"name": "05CA009_PourPoint_PointExutoire",
"crs": { "type": "name", "properties": { "name": "urn:ogc:def:crs:OGC:1.3:CRS84" } },
"features": [
{ "type": "Feature", "properties": { "StationNum": "05CA009", "NameNom": "RED DEER RIVER BELOW BURNT TIMBER CREEK", "Status": "active", "Etat": "en service", "ProvTerr": "AB" }, "geometry": { "type": "Point", "coordinates": [ -115.0182, 51.64634 ] } }
]
}
