{
"type": "FeatureCollection",
"name": "07GB003_Station",
"crs": { "type": "name", "properties": { "name": "urn:ogc:def:crs:OGC:1.3:CRS84" } },
"features": [
{ "type": "Feature", "properties": { "StationNum": "07GB003", "NameNom": "KAKWA RIVER AT HIGHWAY NO. 40", "Status": "active", "Etat": "en service", "ProvTerr": "AB", "HYDAT_ver": "2021-01" }, "geometry": { "type": "Point", "coordinates": [ -118.554, 54.42152 ] } }
]
}
