{
"type": "FeatureCollection",
"name": "10KD009_PourPoint_PointExutoire",
"crs": { "type": "name", "properties": { "name": "urn:ogc:def:crs:OGC:1.3:CRS84" } },
"features": [
{ "type": "Feature", "properties": { "StationNum": "10KD009", "NameNom": "CHICK CREEK ABOVE CHICK LAKE", "Status": "active", "Etat": "en service", "ProvTerr": "NT" }, "geometry": { "type": "Point", "coordinates": [ -128.13539, 65.85462 ] } }
]
}
