{
"type": "FeatureCollection",
"name": "02DD013_Station",
"crs": { "type": "name", "properties": { "name": "urn:ogc:def:crs:OGC:1.3:CRS84" } },
"features": [
{ "type": "Feature", "properties": { "StationNum": "02DD013", "NameNom": "LA VASE RIVER AT NORTH BAY", "Status": "active", "Etat": "en service", "ProvTerr": "ON", "HYDAT_ver": "2021-01" }, "geometry": { "type": "Point", "coordinates": [ -79.39511, 46.26344 ] } }
]
}
