{
"type": "FeatureCollection",
"name": "07HF002_Station",
"crs": { "type": "name", "properties": { "name": "urn:ogc:def:crs:OGC:1.3:CRS84" } },
"features": [
{ "type": "Feature", "properties": { "StationNum": "07HF002", "NameNom": "KEG RIVER AT HIGHWAY NO. 35", "Status": "active", "Etat": "en service", "ProvTerr": "AB", "HYDAT_ver": "2021-01" }, "geometry": { "type": "Point", "coordinates": [ -117.6279, 57.7457 ] } }
]
}
