{
"type": "FeatureCollection",
"name": "05CG006_PourPoint_PointExutoire",
"crs": { "type": "name", "properties": { "name": "urn:ogc:def:crs:OGC:1.3:CRS84" } },
"features": [
{ "type": "Feature", "properties": { "StationNum": "05CG006", "NameNom": "FISH CREEK ABOVE LITTLE FISH LAKE", "Status": "active", "Etat": "en service", "ProvTerr": "AB" }, "geometry": { "type": "Point", "coordinates": [ -112.20248, 51.39074 ] } }
]
}
