{
"type": "FeatureCollection",
"name": "08NM133_dam_data",
"crs": { "type": "name", "properties": { "name": "urn:ogc:def:crs:EPSG::3005" } },
"features": [
{ "type": "Feature", "properties": { "Dam_ID": 3027, "Dam_Number": "D220128-00", "x": -119.8604532908, "y": 49.601058113100002, "Source": "E-Licensing: Derived Centre Point", "Date_Extracted": "2024-01-03T00:00:00", "Dam_Name": "CEROLINI CREEK", "Points_Code": "PD54640", "Dam_Regulated_Code": "Non-Regulated - Including Minor Dam", "Dam_Operation_Code": "Active", "Function": "Main", "Actual_Storage": null, "Total_Licence_Storage": 48105.72, "Admin_Unit": "South Area - Okanagan", "Dam_Type": "Other", "Dam_Height": null, "Crest_Length": null, "Crest_Elevation": null, "Centre_Position_UTM": 11.0, "Centre_Position_Easting": 293322.0, "Centre_Postion_Northing": 5498206.5, "Centre_Lat_Y": 49.60105811, "Centre_Long_X": -119.8604533, "Capable_to_withstand_MDE": null, "Low_Level_Outlet": null, "Spillway_Name": null, "Spillway_Type": null, "Design_Flood_Elevation": null, "Sill_Elevation": null, "Capacity_at_DFE": null, "Inflow_Design_Flood": null, "Owner_Name": "Richard T Pearce (76379)", "Alternate_Contact_Name": null, "Compliance_with_Regulations": "Unknown", "DSO_Assigned": "Moore, Ted C FLNR:EX", "Last_Audit_Date": null, "Years_Since_Last_Audit": null, "Audit_Status": "Not Required", "Audited_This_Year": null, "Regular_Site_Surveil_Confirm_Da": null, "Ann_Formal_Inspection_Confirm_D": null, "OMS_Version_Date": null, "OMS_Received_Date": null, "OMS_Accepted_Date": null, "DEP_Version_Date": null, "DEP_Received_Date": null, "DEP_Accepted_Date": null, "DSR_Version_Date": null, "DSR_Received_Date": null, "DSR_Accepted_Date": null, "Failure_Consequence": "Low", "Risk_Level": "5 - Effectual", "Failure_Probability_Rate": "Small/Very Small", "Deficiency_Type": null, "Deficiency_Description": null, "Deficiency_Created_Date": null, "Deficiency_Resolved_Date": null, "Total_Key_Fields": 26, "Total_Filled": 15, "Total_Missing": 11.0, "Percent_Filled": 0.576923077 }, "geometry": { "type": "Point", "coordinates": [ 1443470.362299999222159, 528664.676500000059605 ] } }
]
}
