{
"type": "FeatureCollection",
"name": "08LB064_Station",
"crs": { "type": "name", "properties": { "name": "urn:ogc:def:crs:OGC:1.3:CRS84" } },
"features": [
{ "type": "Feature", "properties": { "StationNum": "08LB064", "NameNom": "NORTH THOMPSON RIVER AT MCLURE", "Status": "active", "Etat": "en service", "ProvTerr": "BC", "HYDAT_ver": "2021-01" }, "geometry": { "type": "Point", "coordinates": [ -120.2405, 51.04093 ] } }
]
}
