{
"type": "FeatureCollection",
"name": "02DD015_PourPoint_PointExutoire",
"crs": { "type": "name", "properties": { "name": "urn:ogc:def:crs:OGC:1.3:CRS84" } },
"features": [
{ "type": "Feature", "properties": { "StationNum": "02DD015", "NameNom": "COMMANDA CREEK NEAR COMMANDA", "Status": "active", "Etat": "en service", "ProvTerr": "ON" }, "geometry": { "type": "Point", "coordinates": [ -79.60649, 45.94918 ] } }
]
}
