{
"type": "FeatureCollection",
"name": "04GB005_PourPoint_PointExutoire",
"crs": { "type": "name", "properties": { "name": "urn:ogc:def:crs:OGC:1.3:CRS84" } },
"features": [
{ "type": "Feature", "properties": { "StationNum": "04GB005", "NameNom": "BRIGHTSAND RIVER AT MOBERLEY", "Status": "active", "Etat": "en service", "ProvTerr": "ON" }, "geometry": { "type": "Point", "coordinates": [ -90.58099, 49.61198 ] } }
]
}
