{
"type": "FeatureCollection",
"name": "05JA006_Station",
"crs": { "type": "name", "properties": { "name": "urn:ogc:def:crs:OGC:1.3:CRS84" } },
"features": [
{ "type": "Feature", "properties": { "StationNum": "05JA006", "NameNom": "SIX MILE CREEK NEAR GLENTWORTH", "Status": "active", "Etat": "en service", "ProvTerr": "SK", "HYDAT_ver": "2021-01" }, "geometry": { "type": "Point", "coordinates": [ -106.7549, 49.49603 ] } }
]
}
