{
"type": "FeatureCollection",
"name": "08LA001_Station",
"crs": { "type": "name", "properties": { "name": "urn:ogc:def:crs:OGC:1.3:CRS84" } },
"features": [
{ "type": "Feature", "properties": { "StationNum": "08LA001", "NameNom": "CLEARWATER RIVER NEAR CLEARWATER STATION", "Status": "active", "Etat": "en service", "ProvTerr": "BC", "HYDAT_ver": "2021-01" }, "geometry": { "type": "Point", "coordinates": [ -120.066, 51.65572 ] } }
]
}
