{
"type": "FeatureCollection",
"name": "07AG007_Station",
"crs": { "type": "name", "properties": { "name": "urn:ogc:def:crs:OGC:1.3:CRS84" } },
"features": [
{ "type": "Feature", "properties": { "StationNum": "07AG007", "NameNom": "MCLEOD RIVER NEAR ROSEVEAR", "Status": "active", "Etat": "en service", "ProvTerr": "AB", "HYDAT_ver": "2021-01" }, "geometry": { "type": "Point", "coordinates": [ -116.162, 53.69705 ] } }
]
}
