{
"type": "FeatureCollection",
"name": "07GE001_Station",
"crs": { "type": "name", "properties": { "name": "urn:ogc:def:crs:OGC:1.3:CRS84" } },
"features": [
{ "type": "Feature", "properties": { "StationNum": "07GE001", "NameNom": "WAPITI RIVER NEAR GRANDE PRAIRIE", "Status": "active", "Etat": "en service", "ProvTerr": "AB", "HYDAT_ver": "2021-01" }, "geometry": { "type": "Point", "coordinates": [ -118.8029, 55.07125 ] } }
]
}
