{
"type": "FeatureCollection",
"name": "05AB029_PourPoint_PointExutoire",
"crs": { "type": "name", "properties": { "name": "urn:ogc:def:crs:OGC:1.3:CRS84" } },
"features": [
{ "type": "Feature", "properties": { "StationNum": "05AB029", "NameNom": "MEADOW CREEK NEAR THE MOUTH", "Status": "active", "Etat": "en service", "ProvTerr": "AB" }, "geometry": { "type": "Point", "coordinates": [ -113.66342, 49.95416 ] } }
]
}
