{
"type": "FeatureCollection",
"name": "08NA002_PourPoint_PointExutoire",
"crs": { "type": "name", "properties": { "name": "urn:ogc:def:crs:OGC:1.3:CRS84" } },
"features": [
{ "type": "Feature", "properties": { "StationNum": "08NA002", "NameNom": "COLUMBIA RIVER AT NICHOLSON", "Status": "active", "Etat": "en service", "ProvTerr": "BC" }, "geometry": { "type": "Point", "coordinates": [ -116.91256, 51.24421 ] } }
]
}
