{
"type": "FeatureCollection",
"name": "01AL002_Station",
"crs": { "type": "name", "properties": { "name": "urn:ogc:def:crs:OGC:1.3:CRS84" } },
"features": [
{ "type": "Feature", "properties": { "StationNum": "01AL002", "NameNom": "NASHWAAK RIVER AT DURHAM BRIDGE", "Status": "active", "Etat": "en service", "ProvTerr": "NB", "HYDAT_ver": "2021-01" }, "geometry": { "type": "Point", "coordinates": [ -66.61131, 46.12592 ] } }
]
}
