{
"type": "FeatureCollection",
"name": "07JF003_Station",
"crs": { "type": "name", "properties": { "name": "urn:ogc:def:crs:OGC:1.3:CRS84" } },
"features": [
{ "type": "Feature", "properties": { "StationNum": "07JF003", "NameNom": "PONTON RIVER ABOVE BOYER RIVER", "Status": "active", "Etat": "en service", "ProvTerr": "AB", "HYDAT_ver": "2021-01" }, "geometry": { "type": "Point", "coordinates": [ -116.2561, 58.46426 ] } }
]
}
