{
"type": "FeatureCollection",
"name": "15041200_dam_data",
"crs": { "type": "name", "properties": { "name": "urn:ogc:def:crs:EPSG::3005" } },
"features": [
{ "type": "Feature", "properties": { "Dam_ID": 1821, "Dam_Number": "D610000-00", "x": -132.29803789920001, "y": 58.225823144400003, "Source": "BCGW: Derived Centre", "Date_Extracted": "2024-01-03T00:00:00", "Dam_Name": "FLEECE CREEK DAM", "Points_Code": "PD69847", "Dam_Regulated_Code": "Non-Regulated - Including Minor Dam", "Dam_Operation_Code": "Removed", "Function": "Main", "Actual_Storage": null, "Total_Licence_Storage": null, "Admin_Unit": "Dam Safety Section", "Dam_Type": "Earthfill", "Dam_Height": 30.0, "Crest_Length": 125.0, "Crest_Elevation": 1660.0, "Centre_Position_UTM": 8.0, "Centre_Position_Easting": 658677.927, "Centre_Postion_Northing": 6457033.859, "Centre_Lat_Y": 58.22582314, "Centre_Long_X": -132.2980379, "Capable_to_withstand_MDE": null, "Low_Level_Outlet": null, "Spillway_Name": "Spillway 1", "Spillway_Type": "Native Channel Overflow", "Design_Flood_Elevation": null, "Sill_Elevation": 0.0, "Capacity_at_DFE": 0.0, "Inflow_Design_Flood": null, "Owner_Name": "North American Metals Corp (16224)", "Alternate_Contact_Name": null, "Compliance_with_Regulations": "Not Applicable", "DSO_Assigned": "Noseworthy, Mike ENV:EX", "Last_Audit_Date": null, "Years_Since_Last_Audit": null, "Audit_Status": null, "Audited_This_Year": null, "Regular_Site_Surveil_Confirm_Da": null, "Ann_Formal_Inspection_Confirm_D": null, "OMS_Version_Date": null, "OMS_Received_Date": null, "OMS_Accepted_Date": null, "DEP_Version_Date": null, "DEP_Received_Date": null, "DEP_Accepted_Date": null, "DSR_Version_Date": null, "DSR_Received_Date": null, "DSR_Accepted_Date": null, "Failure_Consequence": null, "Risk_Level": "6 - None", "Failure_Probability_Rate": null, "Deficiency_Type": null, "Deficiency_Description": null, "Deficiency_Created_Date": null, "Deficiency_Resolved_Date": null, "Total_Key_Fields": 41, "Total_Filled": 18, "Total_Missing": 23.0, "Percent_Filled": 0.43902439 }, "geometry": { "type": "Point", "coordinates": [ 630554.893699999898672, 1487545.7336 ] } }
]
}
