{
"type": "FeatureCollection",
"name": "02HD009_Station",
"crs": { "type": "name", "properties": { "name": "urn:ogc:def:crs:OGC:1.3:CRS84" } },
"features": [
{ "type": "Feature", "properties": { "StationNum": "02HD009", "NameNom": "WILMOT CREEK NEAR NEWCASTLE", "Status": "active", "Etat": "en service", "ProvTerr": "ON", "HYDAT_ver": "2021-01" }, "geometry": { "type": "Point", "coordinates": [ -78.61881, 43.93022 ] } }
]
}
