{
"type": "FeatureCollection",
"name": "02KD002_Station",
"crs": { "type": "name", "properties": { "name": "urn:ogc:def:crs:OGC:1.3:CRS84" } },
"features": [
{ "type": "Feature", "properties": { "StationNum": "02KD002", "NameNom": "YORK RIVER NEAR BANCROFT", "Status": "active", "Etat": "en service", "ProvTerr": "ON", "HYDAT_ver": "2021-01" }, "geometry": { "type": "Point", "coordinates": [ -77.84603, 45.05214 ] } }
]
}
