{
"type": "FeatureCollection",
"name": "08NA006_Station",
"crs": { "type": "name", "properties": { "name": "urn:ogc:def:crs:OGC:1.3:CRS84" } },
"features": [
{ "type": "Feature", "properties": { "StationNum": "08NA006", "NameNom": "KICKING HORSE RIVER AT GOLDEN", "Status": "active", "Etat": "en service", "ProvTerr": "BC", "HYDAT_ver": "2021-01" }, "geometry": { "type": "Point", "coordinates": [ -116.9721, 51.30118 ] } }
]
}
