{
"type": "FeatureCollection",
"name": "05RC001_PourPoint_PointExutoire",
"crs": { "type": "name", "properties": { "name": "urn:ogc:def:crs:OGC:1.3:CRS84" } },
"features": [
{ "type": "Feature", "properties": { "StationNum": "05RC001", "NameNom": "BERENS RIVER ABOVE BERENS LAKE", "Status": "active", "Etat": "en service", "ProvTerr": "ON" }, "geometry": { "type": "Point", "coordinates": [ -93.52123, 51.80959 ] } }
]
}
