{
"type": "FeatureCollection",
"name": "05OE006_Station",
"crs": { "type": "name", "properties": { "name": "urn:ogc:def:crs:OGC:1.3:CRS84" } },
"features": [
{ "type": "Feature", "properties": { "StationNum": "05OE006", "NameNom": "MANNING CANAL NEAR ILE DES CHENES", "Status": "active", "Etat": "en service", "ProvTerr": "MB", "HYDAT_ver": "2021-01" }, "geometry": { "type": "Point", "coordinates": [ -96.90628, 49.63544 ] } }
]
}
