{
"type": "FeatureCollection",
"name": "02ZH001_Station",
"crs": { "type": "name", "properties": { "name": "urn:ogc:def:crs:OGC:1.3:CRS84" } },
"features": [
{ "type": "Feature", "properties": { "StationNum": "02ZH001", "NameNom": "PIPERS HOLE RIVER AT MOTHERS BROOK", "Status": "active", "Etat": "en service", "ProvTerr": "NL", "HYDAT_ver": "2021-01" }, "geometry": { "type": "Point", "coordinates": [ -54.28433, 47.94667 ] } }
]
}
