{
"type": "FeatureCollection",
"name": "07FA006_Station",
"crs": { "type": "name", "properties": { "name": "urn:ogc:def:crs:OGC:1.3:CRS84" } },
"features": [
{ "type": "Feature", "properties": { "StationNum": "07FA006", "NameNom": "HALFWAY RIVER NEAR FARRELL CREEK", "Status": "active", "Etat": "en service", "ProvTerr": "BC", "HYDAT_ver": "2021-01" }, "geometry": { "type": "Point", "coordinates": [ -121.6285, 56.25075 ] } }
]
}
