{
"type": "FeatureCollection",
"name": "05ND013_PourPoint_PointExutoire",
"crs": { "type": "name", "properties": { "name": "urn:ogc:def:crs:OGC:1.3:CRS84" } },
"features": [
{ "type": "Feature", "properties": { "StationNum": "05ND013", "NameNom": "MOOSE MOUNTAIN CREEK BELOW GRANT DEVINE LAKE", "Status": "active", "Etat": "en service", "ProvTerr": "SK" }, "geometry": { "type": "Point", "coordinates": [ -102.22955, 49.24759 ] } }
]
}
