{
"type": "FeatureCollection",
"name": "08NA005_dam_data",
"crs": { "type": "name", "properties": { "name": "urn:ogc:def:crs:EPSG::3005" } },
"features": [
{ "type": "Feature", "properties": { "Dam_ID": 2143, "Dam_Number": "D330132-00", "x": -116.1195040659, "y": 50.549312330900001, "Source": "E-Licensing: Derived Centre Point", "Date_Extracted": "2024-01-03T00:00:00", "Dam_Name": "LAKE ENID DAM", "Points_Code": "PD24632", "Dam_Regulated_Code": "Regulated", "Dam_Operation_Code": "Active", "Function": "Outlet", "Actual_Storage": null, "Total_Licence_Storage": null, "Admin_Unit": "South Area - Kootenay", "Dam_Type": "Earthfill", "Dam_Height": 0.0, "Crest_Length": 0.0, "Crest_Elevation": 0.0, "Centre_Position_UTM": 11.0, "Centre_Position_Easting": 562380.194, "Centre_Postion_Northing": 5600078.79, "Centre_Lat_Y": 50.54931233, "Centre_Long_X": -116.1195041, "Capable_to_withstand_MDE": null, "Low_Level_Outlet": null, "Spillway_Name": "Spillway 1", "Spillway_Type": "Native Channel Overflow", "Design_Flood_Elevation": null, "Sill_Elevation": 0.0, "Capacity_at_DFE": 0.0, "Inflow_Design_Flood": null, "Owner_Name": "Ducks Unlimited (Canada) (8359)", "Alternate_Contact_Name": "Katharine vanSpall", "Compliance_with_Regulations": "Unknown", "DSO_Assigned": "ONeill, Kevin FLNR:EX", "Last_Audit_Date": "1997-05-22T00:00:00", "Years_Since_Last_Audit": 26.7, "Audit_Status": "Not Required", "Audited_This_Year": "No", "Regular_Site_Surveil_Confirm_Da": null, "Ann_Formal_Inspection_Confirm_D": null, "OMS_Version_Date": null, "OMS_Received_Date": null, "OMS_Accepted_Date": null, "DEP_Version_Date": null, "DEP_Received_Date": null, "DEP_Accepted_Date": null, "DSR_Version_Date": null, "DSR_Received_Date": null, "DSR_Accepted_Date": null, "Failure_Consequence": "Low", "Risk_Level": "5 - Effectual", "Failure_Probability_Rate": "Small/Very Small", "Deficiency_Type": null, "Deficiency_Description": null, "Deficiency_Created_Date": null, "Deficiency_Resolved_Date": null, "Total_Key_Fields": 26, "Total_Filled": 20, "Total_Missing": 6.0, "Percent_Filled": 0.769230769 }, "geometry": { "type": "Point", "coordinates": [ 1697588.812300000339746, 663666.186699999496341 ] } },
{ "type": "Feature", "properties": { "Dam_ID": 2144, "Dam_Number": "D330132-02", "x": -116.12170902539999, "y": 50.538292584399997, "Source": "E-Licensing: Derived Centre Point", "Date_Extracted": "2024-01-03T00:00:00", "Dam_Name": "ENID LAKE (WILMER CREEK) DIVERSION", "Points_Code": "PD24631", "Dam_Regulated_Code": "Non-Regulated - Including Minor Dam", "Dam_Operation_Code": "Not Constructed", "Function": "Main", "Actual_Storage": null, "Total_Licence_Storage": 61674.0, "Admin_Unit": "South Area - Kootenay", "Dam_Type": "Other", "Dam_Height": 0.0, "Crest_Length": 0.0, "Crest_Elevation": 0.0, "Centre_Position_UTM": 11.0, "Centre_Position_Easting": 562238.485, "Centre_Postion_Northing": 5598851.625, "Centre_Lat_Y": 50.53829258, "Centre_Long_X": -116.121709, "Capable_to_withstand_MDE": null, "Low_Level_Outlet": null, "Spillway_Name": "Spillway 1", "Spillway_Type": null, "Design_Flood_Elevation": null, "Sill_Elevation": 0.0, "Capacity_at_DFE": 0.0, "Inflow_Design_Flood": null, "Owner_Name": "Ducks Unlimited (Canada) (8359)", "Alternate_Contact_Name": "Katharine vanSpall", "Compliance_with_Regulations": "No", "DSO_Assigned": "ONeill, Kevin FLNR:EX", "Last_Audit_Date": null, "Years_Since_Last_Audit": null, "Audit_Status": "Not Required", "Audited_This_Year": null, "Regular_Site_Surveil_Confirm_Da": null, "Ann_Formal_Inspection_Confirm_D": null, "OMS_Version_Date": null, "OMS_Received_Date": null, "OMS_Accepted_Date": null, "DEP_Version_Date": null, "DEP_Received_Date": null, "DEP_Accepted_Date": null, "DSR_Version_Date": null, "DSR_Received_Date": null, "DSR_Accepted_Date": null, "Failure_Consequence": "Low", "Risk_Level": "5 - Effectual", "Failure_Probability_Rate": "Small/Very Small", "Deficiency_Type": null, "Deficiency_Description": null, "Deficiency_Created_Date": null, "Deficiency_Resolved_Date": null, "Total_Key_Fields": 26, "Total_Filled": 19, "Total_Missing": 7.0, "Percent_Filled": 0.730769231 }, "geometry": { "type": "Point", "coordinates": [ 1697604.749199999496341, 662429.811799999326468 ] } }
]
}
