{
"type": "FeatureCollection",
"name": "02YL008_PourPoint_PointExutoire",
"crs": { "type": "name", "properties": { "name": "urn:ogc:def:crs:OGC:1.3:CRS84" } },
"features": [
{ "type": "Feature", "properties": { "StationNum": "02YL008", "NameNom": "UPPER HUMBER RIVER ABOVE BLACK BROOK", "Status": "active", "Etat": "en service", "ProvTerr": "NL" }, "geometry": { "type": "Point", "coordinates": [ -57.29404, 49.61823 ] } }
]
}
