{
"type": "FeatureCollection",
"name": "05NF002_Station",
"crs": { "type": "name", "properties": { "name": "urn:ogc:def:crs:OGC:1.3:CRS84" } },
"features": [
{ "type": "Feature", "properties": { "StationNum": "05NF002", "NameNom": "ANTLER RIVER NEAR MELITA", "Status": "active", "Etat": "en service", "ProvTerr": "MB", "HYDAT_ver": "2021-01" }, "geometry": { "type": "Point", "coordinates": [ -101.0493, 49.05739 ] } }
]
}
