{
"type": "FeatureCollection",
"name": "05CC013_PourPoint_PointExutoire",
"crs": { "type": "name", "properties": { "name": "urn:ogc:def:crs:OGC:1.3:CRS84" } },
"features": [
{ "type": "Feature", "properties": { "StationNum": "05CC013", "NameNom": "LASTHILL CREEK NEAR ECKVILLE", "Status": "active", "Etat": "en service", "ProvTerr": "AB" }, "geometry": { "type": "Point", "coordinates": [ -114.45799, 52.3616 ] } }
]
}
