{
"type": "FeatureCollection",
"name": "07BE004_Station",
"crs": { "type": "name", "properties": { "name": "urn:ogc:def:crs:OGC:1.3:CRS84" } },
"features": [
{ "type": "Feature", "properties": { "StationNum": "07BE004", "NameNom": "STONY CREEK NEAR TAWATINAW", "Status": "active", "Etat": "en service", "ProvTerr": "AB", "HYDAT_ver": "2021-01" }, "geometry": { "type": "Point", "coordinates": [ -113.4635, 54.29315 ] } }
]
}
