{
"type": "FeatureCollection",
"name": "07BE004_PourPoint_PointExutoire",
"crs": { "type": "name", "properties": { "name": "urn:ogc:def:crs:OGC:1.3:CRS84" } },
"features": [
{ "type": "Feature", "properties": { "StationNum": "07BE004", "NameNom": "STONY CREEK NEAR TAWATINAW", "Status": "active", "Etat": "en service", "ProvTerr": "AB" }, "geometry": { "type": "Point", "coordinates": [ -113.46383, 54.29321 ] } }
]
}
