{
"type": "FeatureCollection",
"name": "02GE008_PourPoint_PointExutoire",
"crs": { "type": "name", "properties": { "name": "urn:ogc:def:crs:OGC:1.3:CRS84" } },
"features": [
{ "type": "Feature", "properties": { "StationNum": "02GE008", "NameNom": "OXBOW CREEK NEAR KILWORTH", "Status": "active", "Etat": "en service", "ProvTerr": "ON" }, "geometry": { "type": "Point", "coordinates": [ -81.41772, 42.96599 ] } }
]
}
