{
"type": "FeatureCollection",
"name": "06CD002_PourPoint_PointExutoire",
"crs": { "type": "name", "properties": { "name": "urn:ogc:def:crs:OGC:1.3:CRS84" } },
"features": [
{ "type": "Feature", "properties": { "StationNum": "06CD002", "NameNom": "CHURCHILL RIVER ABOVE OTTER RAPIDS", "Status": "active", "Etat": "en service", "ProvTerr": "SK" }, "geometry": { "type": "Point", "coordinates": [ -104.73642, 55.64713 ] } }
]
}
