{
"type": "FeatureCollection",
"name": "05DE007_Station",
"crs": { "type": "name", "properties": { "name": "urn:ogc:def:crs:OGC:1.3:CRS84" } },
"features": [
{ "type": "Feature", "properties": { "StationNum": "05DE007", "NameNom": "ROSE CREEK NEAR ALDER FLATS", "Status": "active", "Etat": "en service", "ProvTerr": "AB", "HYDAT_ver": "2021-01" }, "geometry": { "type": "Point", "coordinates": [ -115.011, 52.92991 ] } }
]
}
