{
"type": "FeatureCollection",
"name": "05FC007_PourPoint_PointExutoire",
"crs": { "type": "name", "properties": { "name": "urn:ogc:def:crs:OGC:1.3:CRS84" } },
"features": [
{ "type": "Feature", "properties": { "StationNum": "05FC007", "NameNom": "YOUNG CREEK NEAR CASTOR", "Status": "active", "Etat": "en service", "ProvTerr": "AB" }, "geometry": { "type": "Point", "coordinates": [ -111.72994, 52.25965 ] } }
]
}
