{
"type": "FeatureCollection",
"name": "08HF013_Station",
"crs": { "type": "name", "properties": { "name": "urn:ogc:def:crs:OGC:1.3:CRS84" } },
"features": [
{ "type": "Feature", "properties": { "StationNum": "08HF013", "NameNom": "SIMPSON CREEK NEAR KOPRINO HARBOUR", "Status": "active", "Etat": "en service", "ProvTerr": "BC", "HYDAT_ver": "2021-01" }, "geometry": { "type": "Point", "coordinates": [ -127.842, 50.51245 ] } }
]
}
