{
"type": "FeatureCollection",
"name": "07BK001_PourPoint_PointExutoire",
"crs": { "type": "name", "properties": { "name": "urn:ogc:def:crs:OGC:1.3:CRS84" } },
"features": [
{ "type": "Feature", "properties": { "StationNum": "07BK001", "NameNom": "LESSER SLAVE RIVER AT SLAVE LAKE", "Status": "active", "Etat": "en service", "ProvTerr": "AB" }, "geometry": { "type": "Point", "coordinates": [ -114.75564, 55.30564 ] } }
]
}
