{
"type": "FeatureCollection",
"name": "05DA009_PourPoint_PointExutoire",
"crs": { "type": "name", "properties": { "name": "urn:ogc:def:crs:OGC:1.3:CRS84" } },
"features": [
{ "type": "Feature", "properties": { "StationNum": "05DA009", "NameNom": "NORTH SASKATCHEWAN RIVER AT WHIRLPOOL POINT", "Status": "active", "Etat": "en service", "ProvTerr": "AB" }, "geometry": { "type": "Point", "coordinates": [ -116.47091, 52.00007 ] } }
]
}
