{
"type": "FeatureCollection",
"name": "08DB001_Station",
"crs": { "type": "name", "properties": { "name": "urn:ogc:def:crs:OGC:1.3:CRS84" } },
"features": [
{ "type": "Feature", "properties": { "StationNum": "08DB001", "NameNom": "NASS RIVER ABOVE SHUMAL CREEK", "Status": "active", "Etat": "en service", "ProvTerr": "BC", "HYDAT_ver": "2021-01" }, "geometry": { "type": "Point", "coordinates": [ -129.085, 55.26225 ] } }
]
}
