{
"type": "FeatureCollection",
"name": "08NN028_Station",
"crs": { "type": "name", "properties": { "name": "urn:ogc:def:crs:OGC:1.3:CRS84" } },
"features": [
{ "type": "Feature", "properties": { "StationNum": "08NN028", "NameNom": "LOST HORSE CREEK NEAR CHRISTIAN VALLEY", "Status": "active", "Etat": "en service", "ProvTerr": "BC", "HYDAT_ver": "2021-01" }, "geometry": { "type": "Point", "coordinates": [ -118.8493, 49.36582 ] } }
]
}
