{
"type": "FeatureCollection",
"name": "02MC028_PourPoint_PointExutoire",
"crs": { "type": "name", "properties": { "name": "urn:ogc:def:crs:OGC:1.3:CRS84" } },
"features": [
{ "type": "Feature", "properties": { "StationNum": "02MC028", "NameNom": "RIVIERE DELISLE NEAR ALEXANDRIA", "Status": "active", "Etat": "en service", "ProvTerr": "ON" }, "geometry": { "type": "Point", "coordinates": [ -74.64326, 45.32699 ] } }
]
}
