{
"type": "FeatureCollection",
"name": "09FA001_Station",
"crs": { "type": "name", "properties": { "name": "urn:ogc:def:crs:OGC:1.3:CRS84" } },
"features": [
{ "type": "Feature", "properties": { "StationNum": "09FA001", "NameNom": "WHITESTONE RIVER NEAR THE MOUTH", "Status": "active", "Etat": "en service", "ProvTerr": "YT", "HYDAT_ver": "2021-01" }, "geometry": { "type": "Point", "coordinates": [ -138.4028, 66.42722 ] } }
]
}
