{
"type": "FeatureCollection",
"name": "10LB007_Station",
"crs": { "type": "name", "properties": { "name": "urn:ogc:def:crs:OGC:1.3:CRS84" } },
"features": [
{ "type": "Feature", "properties": { "StationNum": "10LB007", "NameNom": "TIEDA RIVER NEAR THE MOUTH", "Status": "active", "Etat": "en service", "ProvTerr": "NT", "HYDAT_ver": "2021-01" }, "geometry": { "type": "Point", "coordinates": [ -129.2833, 66.69306 ] } }
]
}
