{
"type": "FeatureCollection",
"name": "02YQ005_Station",
"crs": { "type": "name", "properties": { "name": "urn:ogc:def:crs:OGC:1.3:CRS84" } },
"features": [
{ "type": "Feature", "properties": { "StationNum": "02YQ005", "NameNom": "SALMON RIVER NEAR GLENWOOD", "Status": "active", "Etat": "en service", "ProvTerr": "NL", "HYDAT_ver": "2021-01" }, "geometry": { "type": "Point", "coordinates": [ -54.91689, 49.01128 ] } }
]
}
