{
"type": "FeatureCollection",
"name": "08NJ013_water_licenses",
"crs": { "type": "name", "properties": { "name": "urn:ogc:def:crs:EPSG::3857" } },
"features": [
{ "type": "Feature", "properties": { "Dam_ID": 2148, "Dam_Number": "D350107-00", "x": -117.34988121480001, "y": 49.955648675900001, "Source": "BCGW: Derived Centre", "Date_Extracted": "2024-01-03T00:00:00", "Dam_Name": "BARTLETT CREEK DAM", "Points_Code": "PD27968", "Dam_Regulated_Code": "Regulated", "Dam_Operation_Code": "Active", "Function": "Main", "Actual_Storage": null, "Total_Licence_Storage": null, "Admin_Unit": "South Area - Kootenay", "Dam_Type": "Concrete", "Dam_Height": 0.0, "Crest_Length": 18.3, "Crest_Elevation": 0.0, "Centre_Position_UTM": 11.0, "Centre_Position_Easting": 474902.003, "Centre_Postion_Northing": 5533758.204, "Centre_Lat_Y": 49.95564867, "Centre_Long_X": -117.3498812, "Capable_to_withstand_MDE": null, "Low_Level_Outlet": null, "Spillway_Name": "Spillway 1", "Spillway_Type": "Concrete Overflow", "Design_Flood_Elevation": null, "Sill_Elevation": 0.0, "Capacity_at_DFE": 0.0, "Inflow_Design_Flood": null, "Owner_Name": "Village of Silverton (6286)", "Alternate_Contact_Name": "Leonard Casley (114791)", "Compliance_with_Regulations": "Unknown", "DSO_Assigned": "ONeill, Kevin FLNR:EX", "Last_Audit_Date": null, "Years_Since_Last_Audit": null, "Audit_Status": "Not Required", "Audited_This_Year": null, "Regular_Site_Surveil_Confirm_Da": null, "Ann_Formal_Inspection_Confirm_D": null, "OMS_Version_Date": null, "OMS_Received_Date": null, "OMS_Accepted_Date": null, "DEP_Version_Date": null, "DEP_Received_Date": null, "DEP_Accepted_Date": null, "DSR_Version_Date": null, "DSR_Received_Date": null, "DSR_Accepted_Date": null, "Failure_Consequence": "Low", "Risk_Level": "5 - Effectual", "Failure_Probability_Rate": "Small/Very Small", "Deficiency_Type": null, "Deficiency_Description": null, "Deficiency_Created_Date": null, "Deficiency_Resolved_Date": null, "Total_Key_Fields": 26, "Total_Filled": 19, "Total_Missing": 7.0, "Percent_Filled": 0.730769231 }, "geometry": { "type": "Point", "coordinates": [ -13063329.021469555795193, 6438598.512930795550346 ] } }
]
}
