{
"type": "FeatureCollection",
"name": "05QE012_Station",
"crs": { "type": "name", "properties": { "name": "urn:ogc:def:crs:OGC:1.3:CRS84" } },
"features": [
{ "type": "Feature", "properties": { "StationNum": "05QE012", "NameNom": "LONG-LEGGED RIVER BELOW LONG-LEGGED LAKE", "Status": "active", "Etat": "en service", "ProvTerr": "ON", "HYDAT_ver": "2021-01" }, "geometry": { "type": "Point", "coordinates": [ -93.97019, 50.677 ] } }
]
}
