{
"type": "FeatureCollection",
"name": "05JF011_Station",
"crs": { "type": "name", "properties": { "name": "urn:ogc:def:crs:OGC:1.3:CRS84" } },
"features": [
{ "type": "Feature", "properties": { "StationNum": "05JF011", "NameNom": "COTTONWOOD CREEK NEAR LUMSDEN", "Status": "active", "Etat": "en service", "ProvTerr": "SK", "HYDAT_ver": "2021-01" }, "geometry": { "type": "Point", "coordinates": [ -104.9086, 50.59056 ] } }
]
}
