{
"type": "FeatureCollection",
"name": "01DP004_PourPoint_PointExutoire",
"crs": { "type": "name", "properties": { "name": "urn:ogc:def:crs:OGC:1.3:CRS84" } },
"features": [
{ "type": "Feature", "properties": { "StationNum": "01DP004", "NameNom": "MIDDLE RIVER OF PICTOU AT ROCKLIN", "Status": "active", "Etat": "en service", "ProvTerr": "NS" }, "geometry": { "type": "Point", "coordinates": [ -62.77987, 45.49733 ] } }
]
}
