{
"type": "FeatureCollection",
"name": "02ED013_Station",
"crs": { "type": "name", "properties": { "name": "urn:ogc:def:crs:OGC:1.3:CRS84" } },
"features": [
{ "type": "Feature", "properties": { "StationNum": "02ED013", "NameNom": "WYE RIVER NEAR WYEVALE", "Status": "active", "Etat": "en service", "ProvTerr": "ON", "HYDAT_ver": "2021-01" }, "geometry": { "type": "Point", "coordinates": [ -79.90375, 44.64978 ] } }
]
}
