{
"type": "FeatureCollection",
"name": "02ED017_Station",
"crs": { "type": "name", "properties": { "name": "urn:ogc:def:crs:OGC:1.3:CRS84" } },
"features": [
{ "type": "Feature", "properties": { "StationNum": "02ED017", "NameNom": "HOGG CREEK NEAR VICTORIA HARBOUR", "Status": "active", "Etat": "en service", "ProvTerr": "ON", "HYDAT_ver": "2021-01" }, "geometry": { "type": "Point", "coordinates": [ -79.77897, 44.72606 ] } }
]
}
