{
"type": "FeatureCollection",
"name": "07BB002_Station",
"crs": { "type": "name", "properties": { "name": "urn:ogc:def:crs:OGC:1.3:CRS84" } },
"features": [
{ "type": "Feature", "properties": { "StationNum": "07BB002", "NameNom": "PEMBINA RIVER NEAR ENTWISTLE", "Status": "active", "Etat": "en service", "ProvTerr": "AB", "HYDAT_ver": "2021-01" }, "geometry": { "type": "Point", "coordinates": [ -115.0047, 53.60419 ] } }
]
}
