{
"type": "FeatureCollection",
"name": "01FA001_Station",
"crs": { "type": "name", "properties": { "name": "urn:ogc:def:crs:OGC:1.3:CRS84" } },
"features": [
{ "type": "Feature", "properties": { "StationNum": "01FA001", "NameNom": "RIVER INHABITANTS AT GLENORA", "Status": "active", "Etat": "en service", "ProvTerr": "NS", "HYDAT_ver": "2021-01" }, "geometry": { "type": "Point", "coordinates": [ -61.28611, 45.72025 ] } }
]
}
