{
"type": "FeatureCollection",
"name": "05CC009_PourPoint_PointExutoire",
"crs": { "type": "name", "properties": { "name": "urn:ogc:def:crs:OGC:1.3:CRS84" } },
"features": [
{ "type": "Feature", "properties": { "StationNum": "05CC009", "NameNom": "LLOYD CREEK NEAR BLUFFTON", "Status": "active", "Etat": "en service", "ProvTerr": "AB" }, "geometry": { "type": "Point", "coordinates": [ -114.14723, 52.74021 ] } }
]
}
