{
"type": "FeatureCollection",
"name": "05SD004_PourPoint_PointExutoire",
"crs": { "type": "name", "properties": { "name": "urn:ogc:def:crs:OGC:1.3:CRS84" } },
"features": [
{ "type": "Feature", "properties": { "StationNum": "05SD004", "NameNom": "EAST FISHER RIVER NEAR HODGSON", "Status": "active", "Etat": "en service", "ProvTerr": "MB" }, "geometry": { "type": "Point", "coordinates": [ -97.53305, 51.21491 ] } }
]
}
