{
"type": "FeatureCollection",
"name": "08LC004_dam_data",
"crs": { "type": "name", "properties": { "name": "urn:ogc:def:crs:EPSG::3005" } },
"features": [
{ "type": "Feature", "properties": { "Dam_ID": 3230, "Dam_Number": "D240321-00", "x": -119.0430929986, "y": 50.569136185700003, "Source": "E-Licensing: Centre", "Date_Extracted": "2024-01-03T00:00:00", "Dam_Name": "BRASH CREEK", "Points_Code": "PD60034", "Dam_Regulated_Code": "Regulated", "Dam_Operation_Code": "Active", "Function": "Main", "Actual_Storage": null, "Total_Licence_Storage": null, "Admin_Unit": "South Area - Okanagan", "Dam_Type": "Other", "Dam_Height": 4.6, "Crest_Length": 26.0, "Crest_Elevation": 473.0, "Centre_Position_UTM": 11.0, "Centre_Position_Easting": 355319.2, "Centre_Postion_Northing": 5603905.8, "Centre_Lat_Y": 50.56913619, "Centre_Long_X": -119.043093, "Capable_to_withstand_MDE": null, "Low_Level_Outlet": null, "Spillway_Name": null, "Spillway_Type": null, "Design_Flood_Elevation": null, "Sill_Elevation": null, "Capacity_at_DFE": null, "Inflow_Design_Flood": null, "Owner_Name": "City of Enderby (36944)", "Alternate_Contact_Name": null, "Compliance_with_Regulations": "Unknown", "DSO_Assigned": "Moore, Ted C FLNR:EX", "Last_Audit_Date": null, "Years_Since_Last_Audit": null, "Audit_Status": "Not Required", "Audited_This_Year": null, "Regular_Site_Surveil_Confirm_Da": null, "Ann_Formal_Inspection_Confirm_D": null, "OMS_Version_Date": null, "OMS_Received_Date": null, "OMS_Accepted_Date": null, "DEP_Version_Date": null, "DEP_Received_Date": null, "DEP_Accepted_Date": null, "DSR_Version_Date": null, "DSR_Received_Date": null, "DSR_Accepted_Date": null, "Failure_Consequence": "Low", "Risk_Level": "5 - Effectual", "Failure_Probability_Rate": "Small/Very Small", "Deficiency_Type": null, "Deficiency_Description": null, "Deficiency_Created_Date": null, "Deficiency_Resolved_Date": null, "Total_Key_Fields": 26, "Total_Filled": 17, "Total_Missing": 9.0, "Percent_Filled": 0.653846154 }, "geometry": { "type": "Point", "coordinates": [ 1491764.846599999815226, 641294.946299999952316 ] } }
]
}
