{
"type": "FeatureCollection",
"name": "02YK005_PourPoint_PointExutoire",
"crs": { "type": "name", "properties": { "name": "urn:ogc:def:crs:OGC:1.3:CRS84" } },
"features": [
{ "type": "Feature", "properties": { "StationNum": "02YK005", "NameNom": "SHEFFIELD BROOK NEAR TRANS CANADA HIGHWAY", "Status": "active", "Etat": "en service", "ProvTerr": "NL" }, "geometry": { "type": "Point", "coordinates": [ -56.66829, 49.3383 ] } }
]
}
