{
"type": "FeatureCollection",
"name": "06BB003_Station",
"crs": { "type": "name", "properties": { "name": "urn:ogc:def:crs:OGC:1.3:CRS84" } },
"features": [
{ "type": "Feature", "properties": { "StationNum": "06BB003", "NameNom": "CHURCHILL RIVER NEAR PATUANAK", "Status": "active", "Etat": "en service", "ProvTerr": "SK", "HYDAT_ver": "2021-01" }, "geometry": { "type": "Point", "coordinates": [ -107.7257, 55.92317 ] } }
]
}
