{
"type": "FeatureCollection",
"name": "02HL003_Station",
"crs": { "type": "name", "properties": { "name": "urn:ogc:def:crs:OGC:1.3:CRS84" } },
"features": [
{ "type": "Feature", "properties": { "StationNum": "02HL003", "NameNom": "BLACK RIVER NEAR ACTINOLITE", "Status": "active", "Etat": "en service", "ProvTerr": "ON", "HYDAT_ver": "2021-01" }, "geometry": { "type": "Point", "coordinates": [ -77.36965, 44.5396 ] } }
]
}
