{
"type": "FeatureCollection",
"name": "08MH004_dam_data",
"crs": { "type": "name", "properties": { "name": "urn:ogc:def:crs:EPSG::3005" } },
"features": [
{ "type": "Feature", "properties": { "Dam_ID": 2711, "Dam_Number": "D410003-00", "x": -122.7759167654, "y": 49.353820059100002, "Source": "E-Licensing: Derived Centre Point", "Date_Extracted": "2024-01-03T00:00:00", "Dam_Name": "COQUITLAM DAM", "Points_Code": "PD42777", "Dam_Regulated_Code": "Regulated", "Dam_Operation_Code": "Active", "Function": "Main", "Actual_Storage": null, "Total_Licence_Storage": 247595206.9, "Admin_Unit": "Dam Safety Section", "Dam_Type": "Earthfill", "Dam_Height": 30.5, "Crest_Length": 290.0, "Crest_Elevation": 160.1, "Centre_Position_UTM": 10.0, "Centre_Position_Easting": 516273.596, "Centre_Postion_Northing": 5466813.635, "Centre_Lat_Y": 49.35382006, "Centre_Long_X": -122.7759168, "Capable_to_withstand_MDE": null, "Low_Level_Outlet": null, "Spillway_Name": "Spillway 1", "Spillway_Type": "Concrete Overflow", "Design_Flood_Elevation": 159.6, "Sill_Elevation": 155.5, "Capacity_at_DFE": 1074.0, "Inflow_Design_Flood": null, "Owner_Name": "BC Hydro & Power Authority (64404)", "Alternate_Contact_Name": "Rebecca Polvere (64455)", "Compliance_with_Regulations": "Yes", "DSO_Assigned": "Noseworthy, Mike ENV:EX", "Last_Audit_Date": "2017-11-30T00:00:00", "Years_Since_Last_Audit": 6.1, "Audit_Status": "Backlog", "Audited_This_Year": "No", "Regular_Site_Surveil_Confirm_Da": "2016-01-04T00:00:00", "Ann_Formal_Inspection_Confirm_D": "2017-01-27T00:00:00", "OMS_Version_Date": "2021-03-01T00:00:00", "OMS_Received_Date": null, "OMS_Accepted_Date": "2022-07-15T00:00:00", "DEP_Version_Date": "2022-11-29T00:00:00", "DEP_Received_Date": null, "DEP_Accepted_Date": "2022-07-29T00:00:00", "DSR_Version_Date": null, "DSR_Received_Date": null, "DSR_Accepted_Date": "2022-07-15T00:00:00", "Failure_Consequence": "Extreme", "Risk_Level": "3 - Stable", "Failure_Probability_Rate": "Small/Very Small", "Deficiency_Type": null, "Deficiency_Description": null, "Deficiency_Created_Date": null, "Deficiency_Resolved_Date": null, "Total_Key_Fields": 41, "Total_Filled": 29, "Total_Missing": 12.0, "Percent_Filled": 0.707317073 }, "geometry": { "type": "Point", "coordinates": [ 1234343.939500000327826, 487279.684900000691414 ] } }
]
}
