{
"type": "FeatureCollection",
"name": "05BH016_Station",
"crs": { "type": "name", "properties": { "name": "urn:ogc:def:crs:OGC:1.3:CRS84" } },
"features": [
{ "type": "Feature", "properties": { "StationNum": "05BH016", "NameNom": "WEST NOSE CREEK AT CALGARY", "Status": "active", "Etat": "en service", "ProvTerr": "AB", "HYDAT_ver": "2021-01" }, "geometry": { "type": "Point", "coordinates": [ -114.1412, 51.19012 ] } }
]
}
