{
"type": "FeatureCollection",
"name": "08MH001_dam_data",
"crs": { "type": "name", "properties": { "name": "urn:ogc:def:crs:EPSG::3005" } },
"features": [
{ "type": "Feature", "properties": { "Dam_ID": 3757, "Dam_Number": "D410212-00", "x": -122.00716195939999, "y": 49.005625545500003, "Source": "E-Licensing: Centre", "Date_Extracted": "2024-01-03T00:00:00", "Dam_Name": "FROSST CREEK HYDRO DAM", "Points_Code": "PD184948", "Dam_Regulated_Code": "Non-Regulated - Including Minor Dam", "Dam_Operation_Code": "Application", "Function": "Main", "Actual_Storage": null, "Total_Licence_Storage": null, "Admin_Unit": "Coast - South Coast", "Dam_Type": "Concrete–gravity", "Dam_Height": null, "Crest_Length": null, "Crest_Elevation": null, "Centre_Position_UTM": 10.0, "Centre_Position_Easting": 572610.0, "Centre_Postion_Northing": 5428556.0, "Centre_Lat_Y": 49.00562555, "Centre_Long_X": -122.007162, "Capable_to_withstand_MDE": null, "Low_Level_Outlet": null, "Spillway_Name": null, "Spillway_Type": null, "Design_Flood_Elevation": null, "Sill_Elevation": null, "Capacity_at_DFE": null, "Inflow_Design_Flood": null, "Owner_Name": "Frosst Creek Hydro Inc. (119261)", "Alternate_Contact_Name": null, "Compliance_with_Regulations": "Not Applicable", "DSO_Assigned": "Acharya, Binod FLNR:EX", "Last_Audit_Date": null, "Years_Since_Last_Audit": null, "Audit_Status": "Not Required", "Audited_This_Year": null, "Regular_Site_Surveil_Confirm_Da": null, "Ann_Formal_Inspection_Confirm_D": null, "OMS_Version_Date": null, "OMS_Received_Date": null, "OMS_Accepted_Date": null, "DEP_Version_Date": null, "DEP_Received_Date": null, "DEP_Accepted_Date": null, "DSR_Version_Date": null, "DSR_Received_Date": null, "DSR_Accepted_Date": null, "Failure_Consequence": "Low", "Risk_Level": "5 - Effectual", "Failure_Probability_Rate": "Small/Very Small", "Deficiency_Type": null, "Deficiency_Description": null, "Deficiency_Created_Date": null, "Deficiency_Resolved_Date": null, "Total_Key_Fields": 26, "Total_Filled": 14, "Total_Missing": 12.0, "Percent_Filled": 0.538461538 }, "geometry": { "type": "Point", "coordinates": [ 1292348.373099999502301, 451505.525800000876188 ] } }
]
}
